[
  {
    "metadata": "|2001||Action,Drama,War",
    "rating": {
      "rating": "/10",
      "rating_count": ""
    },
    "title": "The Warrior (2001)",
    "description": "ကိုရီးယားနဲ့ တရုတ်တို့ကြား သံတမန်ဆက်ဆံရေးဟာမင်သံတမန်အဖွဲ့သေသွားချိန်မှစပြီးနှစ်နိုင်ငံကြားဆက်ဆံရေးက ယိုယွင်းခဲ့ရပါတယ်။မင်ဧကရာဇ်က ဂိုလျောသံတမန်တွေကိုသူလျှိုလို့စွပ်စွဲပြီးနယ်နှင်ဒဏ်ပေးပြီး နှင်ထုတ်လိုက်ပါတယ်။အပြန်လမ်းမှာ သံတမန်စစ်သူကြီးတို့အဖွဲ့ဟာ မွန်ဂိုတပ်သား‌တွေပြန်ပေးဆွဲလာတဲ့မင်တိုင်းပြည်ရဲ့ မင်းသမီးလေးကိုမွန်ဂိုတပ်သားတွေလက်ထဲကနေကယ်တင်ဖို့ဖြစ်လာပါတယ်…မင်းသမီးလေးကို အန္တရာယ်ကင်းကင်းနဲ့ မင်တိုင်းပြည်ကို ပြန်ပို့နိုင်ပါ့မလားမွန်ဂိုတွေက‌ရော မင်းသမီးလေးကို ပြန်ခေါ်သွားနိုင်မလားဆိုတာကိုဆက်လက်ကြည့်ရှုလိုက်ပါဦးနော်ခေါင်းဆောင်စိတ်ဓာတ်နဲ့ အနစ်နာခံမှုတွေကိုသေချာလေးရိုက်ပြထားတာမလို့ လုံးဝကိုအချိန်ကုန်မှန်းမသိလိုက်ပဲကြည့်ရတန်စေမယ့်ကားလေးပါနော်File size…  3.98 GB /  1.76 GBQuality… WEB Dl 1080i / 720pFormat… mp4Duration…. 2h 39mGenre …..  Action , WarSubtitle…. Myanmar Subtitle (Hard Sub)Encoder…. Thit San KhantTranslated by Jia",
    "screenshot_links": [
      "https://image.tmdb.org/t/p/w300/gUjWplwrg1Nd7KKfzw1nDgzlfpb.jpg",
      "https://image.tmdb.org/t/p/w300/cIRWgbEgjmxq5qMoPkwWM7tWdu2.jpg",
      "https://image.tmdb.org/t/p/w300/cyyPpadIfzb5B978XDKyXHu0dwv.jpg",
      "https://image.tmdb.org/t/p/w300/dmEG5D9RdSlwrAaBWSAlf5RUpCB.jpg",
      "https://image.tmdb.org/t/p/w300/fYqElEY5bYPVsitkqtdEmx4mAMs.jpg"
    ],
    "thumbnail_link": "https://image.tmdb.org/t/p/w185/i0lpQfqQHN7vEYzSHOk6B65dQbb.jpg",
    "movie_links": [
      {
        "link": "https://usersdrive.com/so2ep1dx966l.html",
        "server": "usersdrive.com",
        "size": "3.98 GB",
        "quality": "1080i"
      },
      {
        "link": "https://yoteshinportal.cc/musa-directors-cut-2001-hdtv-1080-i-cm-tsk-mp-4",
        "server": "yoteshinportal.cc",
        "size": "3.98 GB",
        "quality": "1080i"
      },
      {
        "link": "https://megaup.net/1fKej/Musa.Director_s_Cut.2001.HDTV.1080i_%7BCM%7D_TSK.mp4",
        "server": "megaup.net",
        "size": "3.98 GB",
        "quality": "1080i"
      },
      {
        "link": "https://streamvid.net/0su8otk1niku",
        "server": "streamvid.io",
        "size": "3.98 GB",
        "quality": "1080i"
      },
      {
        "link": "https://usersdrive.com/evqeo9h521bq.html",
        "server": "usersdrive.com",
        "size": "1.76 GB",
        "quality": "720p"
      },
      {
        "link": "https://yoteshinportal.cc/musa-directors-cut-2001-hdtv-720-p-cm-tsk-mp-4",
        "server": "yoteshinportal.cc",
        "size": "1.76 GB",
        "quality": "720p"
      },
      {
        "link": "https://megaup.net/2BF8o/Musa.Director_s_Cut.2001.HDTV.720p_%7BCM%7D_TSK.mp4",
        "server": "megaup.net",
        "size": "1.76 GB",
        "quality": "720p"
      },
      {
        "link": "https://streamvid.net/k3vwits1lcic",
        "server": "streamvid.io",
        "size": "1.76 GB",
        "quality": "720p"
      }
    ],
    "trailer": {
      "video_id": "C7Vg1HcgL8U",
      "video_url": "https://www.youtube.com/watch?v=C7Vg1HcgL8U",
      "embed_url": "https://www.youtube.com/embed/C7Vg1HcgL8U"
    }
  },
  {
    "metadata": "PG-13|2001|3h 3min|Action,Drama,History",
    "rating": {
      "rating": "6.2/10",
      "rating_count": ""
    },
    "title": "Pearl Harbor (2001)",
    "description": "Pearl Harbor 2001====================၁၉၄၁ ခုနှစ်က အမေရိကန်နိုင်ငံ၊ပုလဲဆိပ်ကမ်းကိုဂျပန်တွေလာရောက်တိုက်ခိုက်ခဲ့တဲ့ဖြစ်ရပ်မှန်အပေါ်မူတည်ပြီးရိုက်ကူးထားတဲ့ဇာတ်လမ်းဖြစ်ပါတယ်။ ဖြစ်ရပ်မှန်ဆိုပေမယ့်အဓိကဇာတ်ကောင်တွေကတော့စိတ်ကူးယဥ်သာဖြစ်ပြီးအချစ်ဇာတ်လမ်းအပိုင်းပါထည့်သွင်းထားတာဖြစ်ပါတယ်။ ရေ့ဖ်နဲ့ဒန်နီဟာ ငယ်စဥ်ကတည်းကအချစ်ဆုံးသူငယ်ချင်းတွေဖြစ်ပြီးအမေရိကန်လေတပ်ပိုင်းလော့တွေလည်းဖြစ်ကြပါတယ်။ ရေ့ဖ်ဟာ အက်ဗလင်း ဆိုတဲ့စစ်သူနာပြုနဲ့ချစ်ကြိုက်ပြီးနောက် ဥရောပမှာဖြစ်ပွားနေတဲ့ဒုတိယကမ္ဘာစစ်အတွက်ဗြိတိန်ဘက်မှဝင်တိုက်ပေးဖို့အခွင့်အရေးကိုရရှိသောအခါလက်လွှတ်မခံနိုင်၍ချစ်သူအက်ဗလင်းကိုနှုတ်ဆက်ကာ အင်္ဂလန်သို့ထွက်သွားပါတော့တယ်။ ရေ့ဖ်တစ်ယောက်အင်္ဂလန်မှာဂျာမန်တွေကိုတိုက်ခိုက်နေချိန်မှာ အင်အားနည်းနေတဲ့ပုလဲဆိပ်ကမ်းကိုထင်မှတ်မထားတဲ့အန္တရာယ်ကြီးကျရောက်လာပါတော့တယ်။ဒီဇာတ်လမ်းကိုရိုက်ကူးခဲ့တဲ့ဒါရိုက်တာဟာ Transformers ဇာတ်လမ်းတွေနဲ့နာမည်ကြီးခဲ့တဲ့Michael Bay ဖြစ်တာမို့သူ့ရဲ့အက်ရှင်ပေါက်ကွဲမှုလက်ရာတွေကိုဇာတ်လမ်းတစ်လျှောက်အားရပါးရမြင်တွေ့ရမှာပါ။ အက်ရှင်ကားကြမ်းကြမ်းကြိုက်သူတွေ၊စစ်ဇာတ်လမ်းကြိုက်သူတွေ၊ ဒါရိုက်တာ Michael Bay ရဲ့လက်ရာတွေကြိုက်သူတွေအဖို့တော့ကြည့်သင့်တဲ့ဇာတ်ကားကောင်းတစ်ကားဖြစ်ပါတယ်။Translated by : Pyi T NyeinEncoded by : YKQuality : 1080p blueray and 720p",
    "screenshot_links": [
      "https://image.tmdb.org/t/p/w300/zv1xOEQzebKyku349qDZ085FZlO.jpg",
      "https://image.tmdb.org/t/p/w300/yWk4zAuQdWwLjbKKZDPUBSaTbcU.jpg",
      "https://image.tmdb.org/t/p/w300/f1VBnGgFDghOAt9PApaDGtR2Wuq.jpg",
      "https://image.tmdb.org/t/p/w300/bCJovPf3htouLxGxzDXpnGsC9dw.jpg",
      "https://image.tmdb.org/t/p/w300/lHZwaogchcISnqa2g1wS3ABdSNL.jpg",
      "https://image.tmdb.org/t/p/w300/mPOYZkXGCKXejtCYbrUQnEubHGM.jpg"
    ],
    "thumbnail_link": "https://image.tmdb.org/t/p/w185/ftkKVbk4sQEcekuaGJvpvXcNs32.jpg",
    "movie_links": [
      {
        "link": "https://usersdrive.com/11jzvbumv1ee.html",
        "server": "usersdrive.com",
        "size": "1.93GB",
        "quality": "1080p"
      },
      {
        "link": "https://usersdrive.com/nw3nhav1l9o1.html",
        "server": "usersdrive.com",
        "size": "917MB",
        "quality": "720p"
      },
      {
        "link": "https://veryfiles.com/fkw3u076gdyx",
        "server": "veryfiles.com",
        "size": "1.93GB",
        "quality": "1080p"
      },
      {
        "link": "https://veryfiles.com/uscjvpo0upys",
        "server": "veryfiles.com",
        "size": "917MB",
        "quality": "720p"
      },
      {
        "link": "https://yoteshinportal.cc/pearl-harbor-2001-1080-p-blu-ray-cm-mp-4",
        "server": "yoteshinportal.cc",
        "size": "1.93GB",
        "quality": "1080p"
      },
      {
        "link": "https://yoteshinportal.cc/pearl-harbor-2001-720-p-cm-mp-4",
        "server": "yoteshinportal.cc",
        "size": "917MB",
        "quality": "720p"
      },
      {
        "link": "https://yoteshinportal.cc/yandex/pearl-harbor-2001-1080-p-blu-ray-cm-mp-4",
        "server": "VIP Links",
        "size": "1.93GB",
        "quality": "1080p"
      },
      {
        "link": "https://yoteshinportal.cc/yandex/pearl-harbor-2001-720-p-cm-mp-4",
        "server": "VIP Links",
        "size": "917MB",
        "quality": "720p"
      },
      {
        "link": "https://megaup.net/TQ5o/Pearl.Harbor.2001.1080p.BluRay(CM).mp4",
        "server": "megaup.net",
        "size": "1.93GB",
        "quality": "1080p"
      },
      {
        "link": "https://megaup.net/TQ5e/Pearl.Harbor.2001.720p.(CM).mp4",
        "server": "megaup.net",
        "size": "917MB",
        "quality": "720p"
      },
      {
        "link": "https://www.datbu.com/ayk8kta2g19e.html",
        "server": "datbu.com",
        "size": "1.93MB",
        "quality": "1080p"
      },
      {
        "link": "https://www.datbu.com/p0aycr0qd0b3.html",
        "server": "datbu.com",
        "size": "917MB",
        "quality": "720p"
      },
      {
        "link": "https://mega.nz/file/JWpwFKba#dWwNCdvWXDVoAVBLd-zSVEkQZUiOboDAw7n3Lr1_qIk",
        "server": "mega.nz",
        "size": "1.93GB",
        "quality": "1080p"
      },
      {
        "link": "https://mega.nz/file/RfxEXLRT#WMNVRYRG9qqEE3c9HxBYE0DhCPK9sV_5Oqg4EKymTcQ",
        "server": "mega.nz",
        "size": "917MB",
        "quality": "720p"
      },
      {
        "link": "https://www.cmvipmembers.com/check-movies/pearl-harbor-2001",
        "server": "VIP Links",
        "size": "1.93GB",
        "quality": "1080p"
      }
    ],
    "trailer": {
      "video_id": "oGYcxjywx0o",
      "video_url": "https://www.youtube.com/watch?v=oGYcxjywx0o",
      "embed_url": "https://www.youtube.com/embed/oGYcxjywx0o"
    }
  },
  {
    "metadata": "PG-13|2001|2h 12min|Action,Adventure,Romance",
    "rating": {
      "rating": "6.9/10",
      "rating_count": "169,757"
    },
    "title": "A Knight’s Tale (2001)",
    "description": "A Knight’s Tale (2001)IMDb – 6.9/10_____Rotten – 59%Heath Ledgerရဲ့ ဇာတ်ကားကောင်းတွေထဲက တစ်ခုနဲ့မိတ်ဆက်ပေးချင်ပါတယ်။ ဇာတ်အိမ်ကလည်း ပြောစရာမရှိအောင် ဒရာမာ ရိုးမန့် အဗန်းရှား အက်ရှင် ရသစုံပါတယ်။Friendhood .. Fatherhood.. Sonhood… Loverhoodအစုံအလင်ပါပါတယ်။ ဇာတ်လမ်းရဲ့ အခြေခံကလည်းဂျော့ဖရေး ချောဆာလို့ခေါ်တဲ့ နာမည်ကျော် အလယ်ခေတ်ကဗျာဆရာစာရေးဆရာတစ်ယောက်ကနေ ဆင့်ကူးခံစားထားတာဖြစ်ပြီး ဂျော့ဖရေးချောဆာတို့ အင်္ဂလန်သမိုင်းထဲကမင်းသားအက်ဒဝပ်တို့လို သူတွေလည်း ပါပါတယ်။ကြည်နူးရင်ခုန် အားကျသွားစေမယ့် ရိုမန်တစ်အဆန်ဆုံးSceneတစ်ခု ဟာလည်း တော်တော်အသက်ဝင်ပါတယ်။ခရမ်းချဉ်သီး ၇၉လုံးနဲ့ အိုင်အမ်ဒီဘီ ၆.၉လည်းရထားပါသေးတယ်။စကားမစပ် အဗန်ဂျာဂိုဏ်းဝင် ဗီးရှင်းကြီးကိုလည်းကိုယ်လုံးတီးနဲ့ပဲ ထပ်တွေ့ရဦးမှာပါ။အလယ်ခတ်ကာလမှာ စီးချင်းထိုးပြိုင်ပွဲတွေရှိခဲ့ကြတယ်။ချပ်ဝတ်ဝတ် မြင်းစီးပြီး ထိပ်တုံးထားတဲ့လှံရှည်အတုံးကိုကိုင်ဆွဲ ဟိုဘက်သည်ဘက် ထိုးနှက်တိုက်ခိုက်ကြရတဲ့ပြိုင်ပွဲမျိုးတွေပါ။ ဒီလိုပွဲတွေဟာ မြင့်မြတ်တဲ့မျိုးနွယ်တွေသူကောင်းပြုခံထား ရတဲ့လူတွေကိုသာ ဝင်ပြိုင်ခွင့်ပေးထားတယ်တဲ့။ အဲ့ဒီလို ပြိုင်ပွဲဝင်လူတွေကိုတော့“Knight”လို့ခေါ်ခဲ့ကြတယ်။ Knight တစ်ယောက်ရဲ့တပြည့်လက်ပါးစေကောင်လေးဖြစ်တဲ့ ဝီလီယမ်ဟာစီးချင်းထိုးပွဲတစ်ဝက်တစ်ပျက်မှာ သူ့ဆရာ Knightသေသွားတဲ့အတွက် သူ့ဆရာဟန်ဆောင်ပြီးစီးချင်းဝင်ထိုးရင်း ကလေးကတည်းက Knightဖြစ်ချင်ခဲ့တဲ့ သူ့အိပ်မက်ကို ဖွင့်ဖို့လမ်းပွင့်သွားသတဲ့။သူ့ရဲ့ ငယ်ပေါင်းကြီးဖော်နှစ်ယောက်ဖြစ်တဲ့ဝတ်နဲ့ ရိုလန်တို့်နှစ်ယောက်နဲ့အတူ ပြိုင်ပွဲဆီသွားရင်းသူ့အတွက် မြင့််မြတ်တဲ့မျိုးရိုးဖြစ်ကြောင်း အတုပြုလုပ်ပေးတဲ့လောင်းကစားသမား စာရေးဆရာ ဂျော့ဖရေးချောဆာအမျိုးသမီးစွမ်းဆောင်ရှင်ပန်းပဲသမကိတ်တို့နဲ့ပါဆုံတွေ့ကာ သူ့အိပ်မက်တွေတဖြည်းဖြည်းဖြစ်တည်လာခဲ့တယ်။လိမ်ညာမှုတစ်ခုနဲ့ သာမန်ကောင်လေးတစ်ယောက်ဟာအိပ်မက်တွေနောက်လိုက်ရင်း အချစ်ကိုတွေ့ရှိရင်းသူပြခဲ့တဲ့ သတ္တိတွေကို စာနာမှုတွေကို ကျွန်တော်တို့ခံစားရင်း သူ စခဲ့တဲ့စွန့်စားခန်းတွေ ဘယ်လိုအဆုံးသတ်သွားမလဲဆိုတာ ရင်ခုန်စွာကြည့်ကြရမှာပါ။ကြွေပြီးသား ကြယ်တစ်ပွင့်ရဲ့ လက်ရာခြေရောတွေကိုခံစားသက်ဝင်လိုက်ကြဦးစို့ရဲ့။(အညွှန်းနဲ့ဘာသာပြန်သူကတော့ WiRa Aung ဖြစ်ပါတယ်)File size__( 1.1 GB)Quality__BR-Rip 720pIMDb Rating__6.9/10Format__mp4Duration__02:12:09Type__Action, Adventure, RomanceSubtitle__Myanmar Subtitle (Hardsub)Translated by WiRa AungEncoded by Naing Aung Latt",
    "screenshot_links": [
      "https://image.tmdb.org/t/p/w300/inFHVFQb1qUzSSb8OjQs3B6kmIJ.jpg",
      "https://image.tmdb.org/t/p/w300/tgLCajGjLksF8XdQlphWq5zGuI3.jpg",
      "https://image.tmdb.org/t/p/w300/xVmpVd5C7RDXVXFBDGcnqQzmTBy.jpg",
      "https://image.tmdb.org/t/p/w300/cX3UBYgmhmeHQt626vWMvbptYq4.jpg",
      "https://image.tmdb.org/t/p/w300/yKRDZlnc0E9IRfxSgPGazbYiIxU.jpg",
      "https://image.tmdb.org/t/p/w300/312TdsR5z7wYFYblSbVC0crnYpX.jpg",
      "https://image.tmdb.org/t/p/w300/uHvJNAiczlo2YlgQNIfIvjef9qy.jpg",
      "https://image.tmdb.org/t/p/w300/owpLMshw28hxgYuOCTMgJl1pxDI.jpg",
      "https://image.tmdb.org/t/p/w300/nAh87l7Yl14bDmVPV6Vyf0yImyz.jpg",
      "https://image.tmdb.org/t/p/w300/7BicyhHoUwVx6kBObUwAjMXd9Lu.jpg",
      "https://image.tmdb.org/t/p/w300/2DnpndC7kUVKN41bQoypkKFn1g7.jpg",
      "https://image.tmdb.org/t/p/w300/gkT737kgnmI6jZyXbUBJRwVbGkW.jpg"
    ],
    "thumbnail_link": "https://channelmyanmar.org/wp-content/uploads/2019/04/A-Knight’s-Tale-poster.jpg",
    "movie_links": [
      {
        "link": "https://megaup.net/TTfs/A_Knight’s_Tale_[2001]_(MM_Sub).mp4",
        "server": "megaup.net",
        "size": "1.1 GB",
        "quality": "Blu-Ray 720p"
      },
      {
        "link": "https://mega.nz/file/hIkWHLaI#rwa0RgDpQYtU5_6UReuiSuw-0Wuqv9ExXhRUdRl2Z1I",
        "server": "mega.nz",
        "size": "1.1 GB",
        "quality": "Blu-Ray 720p"
      },
      {
        "link": "https://www.cmvipmembers.com/check-movies/a-knights-tale-2001",
        "server": "VIP Links",
        "size": "1.1 GB",
        "quality": "Blu-Ray 720p"
      },
      {
        "link": "https://yoteshinportal.cc/a-knights-tale-2001-mm-sub-mp-4",
        "server": "yoteshinportal.cc",
        "size": "1.1 GB",
        "quality": "Blu-Ray 720p"
      },
      {
        "link": "https://sbembed3.com/5l313cxzc6bx.html",
        "server": "streamsb.com",
        "size": "1.1 GB",
        "quality": "Blu-Ray 720p"
      }
    ],
    "trailer": {
      "video_id": "zH6U5y086hw",
      "video_url": "https://www.youtube.com/watch?v=zH6U5y086hw",
      "embed_url": "https://www.youtube.com/embed/zH6U5y086hw"
    }
  },
  {
    "metadata": "R|2001|147 min|Drama,Mystery",
    "rating": {
      "rating": "8.0/10",
      "rating_count": "244,555"
    },
    "title": "Mulholland Drive (2001)",
    "description": "“Mulholland Drive” (2001)~~~ ~~~ ~~~ ~~~ ~~~ ~~~Hollywood က ေငြေရာင္ပိတ္ကားေတြထက္မွာ အထင္ေပၚဆံုးသူျဖစ္ဖုိ႕၊ အေက်ာ္ႀကားဆံုးနဲ႕ အရည္အခ်င္းအရွိဆံုး မင္းသမီးအျဖစ္ လူေတြ၀ုိင္းရံေနတဲ့ ေကာ္ေဇာနီေတြေပၚမွာ ေလွ်ာက္လွမ္းႏုိင္ဖုိ႕။ ဒါေတြက အိမ္နဲ႕ေ၀းရာ California က ရုပ္ရွင္ကမၻာကုိ အေရာက္လာခဲ့တဲ့ Betty Elms ရဲ႕ စိတ္ကူးအိပ္မက္ေတြပဲ။City of Angels လုိ႕ သမုတ္ႀကတဲ့ဒီျမိဳ႕ေတာ္က သူ႕အေဒၚရဲ႕ေနအိမ္ကုိ Betty ေရာက္တဲ့အခ်ိန္မွာ၊ သူမေမွ်ာ္လင့္ထားတဲ့ အံ့ႀသစရာတစ္ခုက အဆင္သင့္ေစာင့္ႀကိဳေနတယ္။ အဲဒါကေတာ့၊ အိမ္ထဲမွာ ႀကိဳေရာက္ေနတဲ့၊ အတိတ္ေမ့ေနတဲ့ မိန္းကေလးတစ္ေယာက္နဲ႕ ဆံုရတာပဲ။ သူ႕ရဲ႕အေဒၚနဲ႕လဲ ဆက္စပ္မႈမရွိ၊ ဘာေတြျဖစ္ခဲ့တယ္ဆုိတာကုိလဲ ေမးမရေပမယ့္၊ ရွင္းျပလုိ႕မရႏုိင္တဲ့ ခံစားခ်က္တစ္ခုေႀကာင့္၊ Rita လုိ႕ သူ႕ကုိ္ယ္သူ နာမည္ေပးထားတဲ့ ဒီေကာင္မေလး ဘယ္သူဆုိတာကုိ သိရေအာင္ကူညီေပးဖုိ႕ Betty ဆံုးျဖတ္လုိက္တယ္။သူစိတ္၀င္စားေနတဲ့ ရုပ္ရွင္ဇာတ္ရုပ္တစ္ခုမွာ သရုပ္ေဆာင္ရမယ့္ အခြင့္အေရးကုိ၊ အဆက္အသြယ္ေကာင္းတဲ့ တျခားမင္းသမီးလက္ထဲကုိ လႊဲေပးလုိက္ရတဲ့အခ်ိန္၊ တစ္ဖက္မွာလည္း Rita ခုလုိ အတိတ္ေမ့သြားတာ ေသြးရုိးသားရုိးမဟုတ္တဲ့ မေတာ္တဆမႈတစ္ခုေႀကာင့္ ဆုိတာကုိ သိလုိက္ရတယ္။ ဒီလုိနဲ႕ တစ္စတစ္စ ေပၚလာတဲံ Rita ရဲ႕ ေနာက္ေႀကာင္းကုိ စံုစမ္းရင္း၊ Rita အတိတ္မေမ့ခင္ ေနခဲ့တယ္လုိ႕ ယူဆရတဲ့အိမ္ကုိ သူတုိ႕ေတြေရာက္သြားခ်ိန္မွာ ကိစၥအားလံုးကုိ ပုိျပီး႐ႈပ္ေထြးေစမယ့္ အရာတစ္ခုကုိ ေတြ႕လုိက္ရတဲ့အခါမွာေတာ့ … … … ။IMDB – 8/10Metacritic – 81%Rotten Tomatoes – 82%~~~ ~~~ ~~~ ~~~ ~~~ ~~~ ~~~~~~ ~~~ ~~~ ~~~ ~~~ ~~~ ~~~Naomi Watts နဲ႕ Laura Elena Harring တုိ႕ ဦးေဆာင္ပါ၀င္ထားတဲ့ ဒါရိုက္တာ David Lynch ရဲ႕လက္ရာပါ။ ဒီမင္းသမီးေတြကုိ အႏုပညာလမ္းေႀကာင္းမွန္ေပၚ တင္ေပးႏုိင္ခဲ့သလုိ၊ Lynch ကုိလည္း အကယ္ဒမီဆုအတြက္ nomination ရေစခဲ့တဲ့ Mulholland Drive ကုိ ဒီဒါရုိက္တာႀကီးရဲ႕ အေျပာင္ေျမာက္ဆံုး ဇာတ္ကားေတြထဲ ထိပ္ဆံုးကလုိ႕ ညႊန္းဆုိႀကေလ့ရွိပါတယ္။မူလက ရုပ္သံဇာတ္လမ္းတြဲတစ္ခု ဖန္တီးဖုိ႕ရည္ရြယ္ခ်က္နဲ႕ ဇာတ္သိမ္းမေရရာတဲ့ Pilot Episode အျဖစ္ ရုိက္ကူးခဲ့ေပမယ့္၊ ပယ္ခ်ခံခဲ့ရတဲ့ေနာက္မွာ၊ ရိုက္ထားျပီးသားဇာတ္လမ္းကုိ ဇာတ္သိမ္းခန္း ထပ္မံရုိက္ကူးျဖည့္စြက္ျပီး ရုပ္ရွင္ကားႀကီးအျဖစ္ အသြင္ေျပာင္းခဲ့တာပါ။ ဒီအခ်က္ေႀကာင့္ရယ္၊ Lynch ရဲ႕ ပင္ကုိယ္ရုိက္ကူးမႈပံုစံရယ္ေႀကာင့္၊ Mulholland Drive ရဲ႕ ဇာတ္လမ္းဟာ တိတိက်က်ရယ္လုိ႕ မဟုတ္ပဲ ႀကည့္႐ႈသူရဲ႕ အဓိပၸါယ္ေကာက္မႈအေပၚ မူတည္ျပီး ကြာျခားသြားတတ္တဲ့ သဘာ၀ ရွိေနတာျဖစ္ျပီး၊ အဲဒါကပဲ သူ႕ရဲ႕အဓိကဆြဲေဆာင္မႈ ျဖစ္လာခဲ့ပါတယ္။ရုိက္ကူးထားတဲ့ပံုစံကေတာ့ David Lynch ကားေတြရဲ႕ထံုးစံအတုိင္းပဲ၊ တစ္သမတ္တည္းျဖစ္တဲ့ ဇာတ္လမ္းသြားမဟုတ္သလုိ၊ တစ္ကားလံုးမွာ ကင္မရာအသံုးျပဳနည္းမ်ိဳးစံုကုိ သံုးထားတာေႀကာင့္ ဇာတ္ေကာင္တစ္ေယာက္ခ်င္းစီရဲ႕ အတြင္းစိတ္နဲ႕ အေျခအေနတစ္ခုအေပၚ ဘာေႀကာင့္ဒီလုိတံု႕ျပန္လဲ ဆုိတဲ့အေႀကာင္းရင္းကုိ ႀကည့္ေနတဲ့သူကုိ အတြင္းက်က်ခံစားမိေစပါတယ္။ ဒါ့အျပင္၊ ဇာတ္၀င္ခန္းတုိင္းမွာ အသံုးျပဳထားတဲ့ ေနာက္ခံအသံကလဲ ဒီဇာတ္၀င္ခန္းကေပးခ်င္တဲ့ စုိးရိမ္စိတ္၊ ေႀကာက္စိတ္ အစရွိတဲ့ ခံစားခ်က္ေတြကုိ ပရိသတ္ခံစားမိေအာင္ တြန္းပုိ႕ေပးခဲ့ပါတယ္။2001 ခုႏွစ္၊ Cannes ရုပ္ရွင္ပြဲေတာ္မွာ ပြဲဦးထြက္ျပသခဲ့ျပီး၊ ေ၀ဖန္ေရးဆရာေတြနဲ႕ ပရိသတ္ေတြရဲ႕ အထူးခ်ီးက်ဴးမႈကိုရရွိခဲ့တဲ့ Mulholland Drive ဟာ ေဒၚလာ ၁၅ သန္း အကုန္အက်ခံ ရုိက္ကူးခဲ့တာျဖစ္ျပီး၊ ကမၻာတစ္၀ွမ္း စုစုေပါင္း၀င္ေငြ သန္း ၂၀ ေက်ာ္ ျပန္ရခဲ့ပါတယ္။ ဒါေတြကေတာ့ Mulholland Drive ရဲ႕ Wikipedia article က fact ေတြ သက္သက္ရယ္ပါ။ ေျပာခ်င္တာကေတာ့၊ Mulholland Drive ကုိ ပထမဆံုး ႀကည့္မိတဲ့အခ်ိန္မွာ ကင္မရာရုိက္ခ်က္ေတြနဲ႕ ပတ္သတ္တဲ့အရာေတြ၊ ေနာက္ခံအသံေတြ၊ အဲဒီလုိအရာေတြကုိ ဂရုမစုိက္အားခဲ့ဘူး ဆုိတာပါပဲ။ ဒါ့ေႀကာင့္ အခုေျပာျပမယ့္ ကြ်န္ေတာ့္အျမင္ ဆုိတာကလဲ၊ review ဆုိတာထက္၊ ပရိသတ္တစ္ေယာက္အေနနဲ႕ႀကည့္ျပီး ခံစားရတဲ့ ကုိယ္ပုိင္ခံစားခ်က္သက္သက္ပါ။ဒါရုိက္တာႀကီး David Lynch ရဲ႕လက္ရာေတြထဲ ပထမဆံုးႀကည့္မိတဲ့ ဒီကားထဲ ေမ်ာေနရင္း ပထမဆံုး ရလုိက္တာက အိပ္မက္မက္ေနရတဲ့ ဖီလ္လင္ပါပဲ။ ဇာတ္လမ္းဟာ ကစဥ့္ကလ်ားနဲ႕ အစီအစဥ္မက်ဘူး။ ဒါေပမယ့္၊ အဲဒီအပုိင္းအစေလးေတြကပဲ အာရံုကုိ တျခားမလႊဲႏုိင္ေအာင္ ဆြဲေဆာင္ထားတယ္။ အဆက္အစပ္မရွိတဲ့ ဇာတ္၀င္ခန္းေတြ တစ္ခုေပၚတစ္ခု ထပ္လာတဲ့အခ်ိန္မွာ၊ စိတ္႐ႈပ္ေထြးသြားရမယ့္အစား၊ ဘာေတြထပ္ျမင္ရမလဲဆုိတဲ့ စူးစမ္းစိတ္ကသာ ပုိလာတယ္။ အဓိပၸါယ္ ေရေရရာရာ မထင္ရွားတဲ့ ကမၻာတစ္ခုထဲကုိ ေရာက္ေနေပမယ့္၊ ကသိကေအာက္ျဖစ္မေနပဲ အခ်ိန္တန္ရင္ အားလံုးဆက္စပ္မိမွာပါဆုိတဲ့ အာမခံခ်က္ေလးက စိတ္ထဲမွာ အလုိလုိေရာက္ႏွင့္ေနတယ္။တကယ္လည္း ဇာတ္လမ္းဆံုးတဲ့အခါမွာ၊ ဇာတ္လမ္းေရွ႕ပို္င္း တစ္၀က္ေက်ာ္ေက်ာ္ေလာက္ ႀကည့္ခဲ့ရတဲ့ ဟုိေရာက္ဒီေရာက္ျဖစ္ေနတဲ့ ဇာတ္အိမ္ငယ္ေတြက အစပ္အဟပ္တည့္သြားတယ္။ ဒါေပမယ့္၊ ထူးျခားခ်က္က အဲဒီဇာတ္လမ္းအပုိင္းအစေလးေတြရဲ႕ အဓိပၸါယ္ဟာ ဇာတ္သိမ္းတဲ့အထိ သတ္သတ္မွတ္မွတ္မရွိပဲ၊ ကုိယ္အဓိပါၸယ္ဖြင့္ခ်င္သလုိ ဖြင့္လုိရေနတာပဲ။ အဲဒါေႀကာင့္ပဲ၊ ဒီဒါရုိက္တာႀကီးက သူ႕ဇာတ္ကားရဲ႕ အဓိကလုိရင္းက ဘာဆုိတာကုိ ရွင္းရွင္းလင္းလင္းထုတ္ေျပာဖုိ႕ ျငင္းခဲ့တယ္ဆုိတာ နားလည္သြားရတယ္။ဒါ့အျပင္၊ Betty Elms နဲ႕ Diane Selwyn, Rita နဲ႕ Camilla Rhodes တုိ႕ေတြ ဘယ္လုိဆက္စပ္မွူရွိေနလဲ၊ ဇာတ္လမ္းအစမွာ ႀကားခဲ့ရတဲ့ Betty ရဲ႕ စကားေလးတစ္ခြန္းဟာ ေနာက္ပုိင္း Diane ရဲ႕ အမူအက်င့္ကုိ ဘယ္လုိသက္ေရာက္ေနလဲ။ ဇာတ္သိမ္းမွာ ေတြ႕ရတဲ့ Camilla ရဲ႕ စရုိက္က Rita နဲ႕ Betty တုိ႕ရဲ႕ ကနဦးဆက္ဆံေရးကုိ ဘယ္လုိပံုေဖာ္ခဲ့သလဲ။ ဒီလုိေမးခြန္းေတြအမ်ားႀကီး ကုိယ့္ကုိယ္ကုိ ျပန္ေမးေနရင္း၊ ရလာတဲ့အေျဖက တစ္ခုတည္းမဟုတ္သလုိ၊ ဒီအေျဖတစ္ခုခ်င္းကလဲ အဓိပၸါယ္ရွိေနတာေတြက Mulholland Drive ကုိ ႀကည့္ျပီး ႀကိဳက္သည္ျဖစ္ေစ၊ မႀကိဳက္သည္ျဖစ္ေစ၊ ဒီကားနဲ႕ပတ္သတ္တဲ့ ကုိယ့္အျမင္ကုိ ထုတ္ေျပာမွျဖစ္မယ္ဆုိတဲ့ ပရိသတ္ေတြ ခ်င္ျခင္းတက္မႈရဲ႕ အဓိကအေႀကာင္းရင္းပါပဲ။အခုဒီလုိေတြ ေျပာေနေပမယ့္၊ ဒီကားရဲ႕အရသာကုိ တကယ္နားလည္ဖုိ႕က ကုိယ္တုိင္ႀကည့္လုိက္မွ ျဖစ္မွာပါ။ Psychological Thriller ေတြကုိ အရသာေတြ႕တဲ့သူေတြ၊ ေတြးစရာေပးတဲ့ ဇာတ္ကားမ်ိဳးကုိ သေဘာက်ပါတယ္ဆုိတဲ့သူေတြ သာမက၊ ရုပ္ရွင္ကုိ ၀ါသနာပါသူမွန္ရင္ လက္မလႊတ္သင့္တဲ့ ဇာတ္ကားပါပဲ။ တကယ္ႀကည့္ျဖစ္မယ့္သူေတြ အရသာမပ်က္ေအာင္ ဒီပုိ႕စ္မွာ spoiler မထည့္ထားေပမယ့္၊ တကယ္လုိ႕ တျခား review ေတြဖတ္ျပီးသား၊ ဇာတ္လမ္းသြားသိျပီးသားမုိ႕၊ မႀကည့္ေတာ့ဘူးဆုိရင္ေတာ့ နစ္နာမယ္လုိ႕ပဲ ေျပာပါရေစ။#MMDB_Previews#MulhollandDrive#DavidLynch#ASW(ရုပ္ရွင္အညႊန္းကိုM-MDB Pageမွကူးယူေဖာ္ျပပါသည္။)[“Mulholland Drive” (2001)~~~ ~~~ ~~~ ~~~ ~~~ ~~~Hollywood က ငွေရောင်ပိတ်ကားတွေထက်မှာ အထင်ပေါ်ဆုံးသူဖြစ်ဖို့၊ အကျော်ကြားဆုံးနဲ့ အရည်အချင်းအရှိဆုံး မင်းသမီးအဖြစ် လူတွေဝိုင်းရံနေတဲ့ ကော်ဇောနီတွေပေါ်မှာ လျှောက်လှမ်းနိုင်ဖို့။ ဒါတွေက အိမ်နဲ့ဝေးရာ California က ရုပ်ရှင်ကမ္ဘာကို အရောက်လာခဲ့တဲ့ Betty Elms ရဲ့ စိတ်ကူးအိပ်မက်တွေပဲ။City of Angels လို့ သမုတ်ကြတဲ့ဒီမြို့တော်က သူ့အဒေါ်ရဲ့နေအိမ်ကို Betty ရောက်တဲ့အချိန်မှာ၊ သူမမျှော်လင့်ထားတဲ့ အံ့သြစရာတစ်ခုက အဆင်သင့်စောင့်ကြိုနေတယ်။ အဲဒါကတော့၊ အိမ်ထဲမှာ ကြိုရောက်နေတဲ့၊ အတိတ်မေ့နေတဲ့ မိန်းကလေးတစ်ယောက်နဲ့ ဆုံရတာပဲ။ သူ့ရဲ့အဒေါ်နဲ့လဲ ဆက်စပ်မှုမရှိ၊ ဘာတွေဖြစ်ခဲ့တယ်ဆိုတာကိုလဲ မေးမရပေမယ့်၊ ရှင်းပြလို့မရနိုင်တဲ့ ခံစားချက်တစ်ခုကြောင့်၊ Rita လို့ သူ့ကိုယ်သူ နာမည်ပေးထားတဲ့ ဒီကောင်မလေး ဘယ်သူဆိုတာကို သိရအောင်ကူညီပေးဖို့ Betty ဆုံးဖြတ်လိုက်တယ်။သူစိတ်ဝင်စားနေတဲ့ ရုပ်ရှင်ဇာတ်ရုပ်တစ်ခုမှာ သရုပ်ဆောင်ရမယ့် အခွင့်အရေးကို၊ အဆက်အသွယ်ကောင်းတဲ့ တခြားမင်းသမီးလက်ထဲကို လွှဲပေးလိုက်ရတဲ့အချိန်၊ တစ်ဖက်မှာလည်း Rita ခုလို အတိတ်မေ့သွားတာ သွေးရိုးသားရိုးမဟုတ်တဲ့ မတော်တဆမှုတစ်ခုကြောင့် ဆိုတာကို သိလိုက်ရတယ်။ ဒီလိုနဲ့ တစ်စတစ်စ ပေါ်လာတဲံ Rita ရဲ့ နောက်ကြောင်းကို စုံစမ်းရင်း၊ Rita အတိတ်မမေ့ခင် နေခဲ့တယ်လို့ ယူဆရတဲ့အိမ်ကို သူတို့တွေရောက်သွားချိန်မှာ ကိစ္စအားလုံးကို ပိုပြီးရှုပ်ထွေးစေမယ့် အရာတစ်ခုကို တွေ့လိုက်ရတဲ့အခါမှာတော့ … … … ။IMDB – 8/10Metacritic – 81%Rotten Tomatoes – 82%~~~ ~~~ ~~~ ~~~ ~~~ ~~~ ~~~~~~ ~~~ ~~~ ~~~ ~~~ ~~~ ~~~Naomi Watts နဲ့ Laura Elena Harring တို့ ဦးဆောင်ပါဝင်ထားတဲ့ ဒါရိုက်တာ David Lynch ရဲ့လက်ရာပါ။ ဒီမင်းသမီးတွေကို အနုပညာလမ်းကြောင်းမှန်ပေါ် တင်ပေးနိုင်ခဲ့သလို၊ Lynch ကိုလည်း အကယ်ဒမီဆုအတွက် nomination ရစေခဲ့တဲ့ Mulholland Drive ကို ဒီဒါရိုက်တာကြီးရဲ့ အပြောင်မြောက်ဆုံး ဇာတ်ကားတွေထဲ ထိပ်ဆုံးကလို့ ညွှန်းဆိုကြလေ့ရှိပါတယ်။မူလက ရုပ်သံဇာတ်လမ်းတွဲတစ်ခု ဖန်တီးဖို့ရည်ရွယ်ချက်နဲ့ ဇာတ်သိမ်းမရေရာတဲ့ Pilot Episode အဖြစ် ရိုက်ကူးခဲ့ပေမယ့်၊ ပယ်ချခံခဲ့ရတဲ့နောက်မှာ၊ ရိုက်ထားပြီးသားဇာတ်လမ်းကို ဇာတ်သိမ်းခန်း ထပ်မံရိုက်ကူးဖြည့်စွက်ပြီး ရုပ်ရှင်ကားကြီးအဖြစ် အသွင်ပြောင်းခဲ့တာပါ။ ဒီအချက်ကြောင့်ရယ်၊ Lynch ရဲ့ ပင်ကိုယ်ရိုက်ကူးမှုပုံစံရယ်ကြောင့်၊ Mulholland Drive ရဲ့ ဇာတ်လမ်းဟာ တိတိကျကျရယ်လို့ မဟုတ်ပဲ ကြည့်ရှုသူရဲ့ အဓိပ္ပါယ်ကောက်မှုအပေါ် မူတည်ပြီး ကွာခြားသွားတတ်တဲ့ သဘာ၀ ရှိနေတာဖြစ်ပြီး၊ အဲဒါကပဲ သူ့ရဲ့အဓိကဆွဲဆောင်မှု ဖြစ်လာခဲ့ပါတယ်။ရိုက်ကူးထားတဲ့ပုံစံကတော့ David Lynch ကားတွေရဲ့ထုံးစံအတိုင်းပဲ၊ တစ်သမတ်တည်းဖြစ်တဲ့ ဇာတ်လမ်းသွားမဟုတ်သလို၊ တစ်ကားလုံးမှာ ကင်မရာအသုံးပြုနည်းမျိုးစုံကို သုံးထားတာကြောင့် ဇာတ်ကောင်တစ်ယောက်ချင်းစီရဲ့ အတွင်းစိတ်နဲ့ အခြေအနေတစ်ခုအပေါ် ဘာကြောင့်ဒီလိုတုံ့ပြန်လဲ ဆိုတဲ့အကြောင်းရင်းကို ကြည့်နေတဲ့သူကို အတွင်းကျကျခံစားမိစေပါတယ်။ ဒါ့အပြင်၊ ဇာတ်ဝင်ခန်းတိုင်းမှာ အသုံးပြုထားတဲ့ နောက်ခံအသံကလဲ ဒီဇာတ်ဝင်ခန်းကပေးချင်တဲ့ စိုးရိမ်စိတ်၊ ကြောက်စိတ် အစရှိတဲ့ ခံစားချက်တွေကို ပရိသတ်ခံစားမိအောင် တွန်းပို့ပေးခဲ့ပါတယ်။2001 ခုနှစ်၊ Cannes ရုပ်ရှင်ပွဲတော်မှာ ပွဲဦးထွက်ပြသခဲ့ပြီး၊ ဝေဖန်ရေးဆရာတွေနဲ့ ပရိသတ်တွေရဲ့ အထူးချီးကျူးမှုကိုရရှိခဲ့တဲ့ Mulholland Drive ဟာ ဒေါ်လာ ၁၅ သန်း အကုန်အကျခံ ရိုက်ကူးခဲ့တာဖြစ်ပြီး၊ ကမ္ဘာတစ်ဝှမ်း စုစုပေါင်းဝင်ငွေ သန်း ၂၀ ကျော် ပြန်ရခဲ့ပါတယ်။ ဒါတွေကတော့ Mulholland Drive ရဲ့ Wikipedia article က fact တွေ သက်သက်ရယ်ပါ။ ပြောချင်တာကတော့၊ Mulholland Drive ကို ပထမဆုံး ကြည့်မိတဲ့အချိန်မှာ ကင်မရာရိုက်ချက်တွေနဲ့ ပတ်သတ်တဲ့အရာတွေ၊ နောက်ခံအသံတွေ၊ အဲဒီလိုအရာတွေကို ဂရုမစိုက်အားခဲ့ဘူး ဆိုတာပါပဲ။ ဒါ့ကြောင့် အခုပြောပြမယ့် ကျွန်တော့်အမြင် ဆိုတာကလဲ၊ review ဆိုတာထက်၊ ပရိသတ်တစ်ယောက်အနေနဲ့ကြည့်ပြီး ခံစားရတဲ့ ကိုယ်ပိုင်ခံစားချက်သက်သက်ပါ။ဒါရိုက်တာကြီး David Lynch ရဲ့လက်ရာတွေထဲ ပထမဆုံးကြည့်မိတဲ့ ဒီကားထဲ မျောနေရင်း ပထမဆုံး ရလိုက်တာက အိပ်မက်မက်နေရတဲ့ ဖီလ်လင်ပါပဲ။ ဇာတ်လမ်းဟာ ကစဉ့်ကလျားနဲ့ အစီအစဉ်မကျဘူး။ ဒါပေမယ့်၊ အဲဒီအပိုင်းအစလေးတွေကပဲ အာရုံကို တခြားမလွှဲနိုင်အောင် ဆွဲဆောင်ထားတယ်။ အဆက်အစပ်မရှိတဲ့ ဇာတ်ဝင်ခန်းတွေ တစ်ခုပေါ်တစ်ခု ထပ်လာတဲ့အချိန်မှာ၊ စိတ်ရှုပ်ထွေးသွားရမယ့်အစား၊ ဘာတွေထပ်မြင်ရမလဲဆိုတဲ့ စူးစမ်းစိတ်ကသာ ပိုလာတယ်။ အဓိပ္ပါယ် ရေရေရာရာ မထင်ရှားတဲ့ ကမ္ဘာတစ်ခုထဲကို ရောက်နေပေမယ့်၊ ကသိကအောက်ဖြစ်မနေပဲ အချိန်တန်ရင် အားလုံးဆက်စပ်မိမှာပါဆိုတဲ့ အာမခံချက်လေးက စိတ်ထဲမှာ အလိုလိုရောက်နှင့်နေတယ်။တကယ်လည်း ဇာတ်လမ်းဆုံးတဲ့အခါမှာ၊ ဇာတ်လမ်းရှေ့ပိုင်း တစ်ဝက်ကျော်ကျော်လောက် ကြည့်ခဲ့ရတဲ့ ဟိုရောက်ဒီရောက်ဖြစ်နေတဲ့ ဇာတ်အိမ်ငယ်တွေက အစပ်အဟပ်တည့်သွားတယ်။ ဒါပေမယ့်၊ ထူးခြားချက်က အဲဒီဇာတ်လမ်းအပိုင်းအစလေးတွေရဲ့ အဓိပ္ပါယ်ဟာ ဇာတ်သိမ်းတဲ့အထိ သတ်သတ်မှတ်မှတ်မရှိပဲ၊ ကိုယ်အဓိပါ္ပယ်ဖွင့်ချင်သလို ဖွင့်လိုရနေတာပဲ။ အဲဒါကြောင့်ပဲ၊ ဒီဒါရိုက်တာကြီးက သူ့ဇာတ်ကားရဲ့ အဓိကလိုရင်းက ဘာဆိုတာကို ရှင်းရှင်းလင်းလင်းထုတ်ပြောဖို့ ငြင်းခဲ့တယ်ဆိုတာ နားလည်သွားရတယ်။ဒါ့အပြင်၊ Betty Elms နဲ့ Diane Selwyn, Rita နဲ့ Camilla Rhodes တို့တွေ ဘယ်လိုဆက်စပ်မှူရှိနေလဲ၊ ဇာတ်လမ်းအစမှာ ကြားခဲ့ရတဲ့ Betty ရဲ့ စကားလေးတစ်ခွန်းဟာ နောက်ပိုင်း Diane ရဲ့ အမူအကျင့်ကို ဘယ်လိုသက်ရောက်နေလဲ။ ဇာတ်သိမ်းမှာ တွေ့ရတဲ့ Camilla ရဲ့ စရိုက်က Rita နဲ့ Betty တို့ရဲ့ ကနဦးဆက်ဆံရေးကို ဘယ်လိုပုံဖော်ခဲ့သလဲ။ ဒီလိုမေးခွန်းတွေအများကြီး ကိုယ့်ကိုယ်ကို ပြန်မေးနေရင်း၊ ရလာတဲ့အဖြေက တစ်ခုတည်းမဟုတ်သလို၊ ဒီအဖြေတစ်ခုချင်းကလဲ အဓိပ္ပါယ်ရှိနေတာတွေက Mulholland Drive ကို ကြည့်ပြီး ကြိုက်သည်ဖြစ်စေ၊ မကြိုက်သည်ဖြစ်စေ၊ ဒီကားနဲ့ပတ်သတ်တဲ့ ကိုယ့်အမြင်ကို ထုတ်ပြောမှဖြစ်မယ်ဆိုတဲ့ ပရိသတ်တွေ ချင်ခြင်းတက်မှုရဲ့ အဓိကအကြောင်းရင်းပါပဲ။အခုဒီလိုတွေ ပြောနေပေမယ့်၊ ဒီကားရဲ့အရသာကို တကယ်နားလည်ဖို့က ကိုယ်တိုင်ကြည့်လိုက်မှ ဖြစ်မှာပါ။ Psychological Thriller တွေကို အရသာတွေ့တဲ့သူတွေ၊ တွေးစရာပေးတဲ့ ဇာတ်ကားမျိုးကို သဘောကျပါတယ်ဆိုတဲ့သူတွေ သာမက၊ ရုပ်ရှင်ကို ဝါသနာပါသူမှန်ရင် လက်မလွှတ်သင့်တဲ့ ဇာတ်ကားပါပဲ။ တကယ်ကြည့်ဖြစ်မယ့်သူတွေ အရသာမပျက်အောင် ဒီပို့စ်မှာ spoiler မထည့်ထားပေမယ့်၊ တကယ်လို့ တခြား review တွေဖတ်ပြီးသား၊ ဇာတ်လမ်းသွားသိပြီးသားမို့၊ မကြည့်တော့ဘူးဆိုရင်တော့ နစ်နာမယ်လို့ပဲ ပြောပါရစေ။#MMDB_Previews#MulhollandDrive#DavidLynch#ASW(ရုပ်ရှင်အညွှန်းကို M-MDB Page မှကူးယူဖော်ပြပါသည်။)]File size…(1GB)Quality…BR-Rip 720pFormat…mp4Duration….02:26:34Subtitle….Myanmar Subtitle (Hardsub)Encoder….Nyeinsaeya Aung",
    "screenshot_links": [],
    "thumbnail_link": "https://channelmyanmar.org/wp-content/uploads/2017/01/5VX1HIn.jpg",
    "movie_links": [
      {
        "link": "https://mega.nz/file/YkZCSRSY#S-_2edZxnZLAPX747Jm2Z4hWMsMzICzd-sdZtK30ryA",
        "server": "mega.nz",
        "size": "1GB",
        "quality": "720P"
      },
      {
        "link": "https://upstream.to/yattqicwldqk",
        "server": "upstream.to",
        "size": "1GB",
        "quality": "720P"
      },
      {
        "link": "https://yoteshinportal.cc/mulholland-drive-2001-mm-sub-mp-4",
        "server": "yoteshinportal.cc",
        "size": "1GB",
        "quality": "720p"
      }
    ],
    "trailer": null
  },
  {
    "metadata": "|2001||Action,Mystery,Thriller",
    "rating": {
      "rating": "6.3/10",
      "rating_count": "3100"
    },
    "title": "When Strangers Appear (2001)",
    "description": "When Strangers Appear (2001)=======================IMDb Rating – 6.3/10ဘတ်သ်တစ်ယောက် လူသူအလာကြဲလှတဲ့ သူ့ရဲ့လမ်းဘေးစားသောက်ဆိုင်လေးကို တစ်နေ့တာအတွက်စတင်ဖွင့်ချိန်မှာသူ့အတွက် သာမန်ပျင်းရိဖွယ်နေ့တစ်နေ့လို့ထင်ခဲ့မိပါတယ်။ ဒါပေမယ့်လည်း ဂျက်ခ်ဆိုတဲ့ ဒဏ်ရာရထားတဲ့ red flag တွေအပြည့်နဲ့လူချောလေးတစ်ယောက် ဆိုင်ထဲကိုဝင်လာချိန်မှာတော့ သူ့အထင်မှားသွားပြီဆိုတာ စသိလိုက်ရပါတယ်။ငနဲသားဟာ ထိတ်ထိတ်ပျာပျာရှိလွန်းတယ်၊ လက်ထဲမှာလည်း အကြွေစေ့တွေပဲပါတယ်။ ဘတ်သ်ကတော့ ဒါနပြုလိုက်တယ်လို့ သဘောထားပြီး သူ့ကိုမနက်စာကျွေးနေချိန်မှာ နောက်ထပ် လူရမ်းကားပုံစံနဲ့လူသုံးယောက်ဆိုင်ထဲထပ်ဝင်လာပါတယ်။ သူတို့အုပ်စုခေါင်းဆောင်ကလည်း လူချောတစ်ယောက်ပါပဲ။အဲ့ဒီအချိန်မှာ ဂျက်ခ်တစ်ယောက် စားပွဲမှာထိုင်နေရာကနေပျောက်သွားပြီး တစ်နေရာမှာ ဝင်ပုန်းနေတဲ့အချိန်မှာ ဘတ်သ် တစ်စုံတစ်ခုကိုသတိထားမိလိုက်ပါတော့တယ်။ အဲ့ဒါကတော့ ပထမကောင်လေး ဂျက်ခ်နောက်ကိုဒီလူရမ်းကားသုံးယောက်က အကြောင်းတစ်စုံတစ်ရာအတွက် လိုက်အန္တရာယ်ပေးနေတယ်ဆိုတာပါပဲ။ ဒီနေ့တစ်နေ့တာဟာ သူ့အတွက် ဘယ်လိုမှပျင်းစရာမကောင်းတော့ဘူးဆိုတာ သေချာသွားပါပြီ။အခုချိန်မှာသိပ်မတွေ့ရတော့တဲ့ psychological thriller ကားကောင်းတစ်ကားဖြစ်ပြီးအစကနေအဆုံးအထိ လှည့်ကွက်တွေအပြည့်နဲ့ဆွဲခေါ်သွားပါလိမ့်မယ်။Josh Lucas , Radha Mitchell နဲ့ Barry Watson တို့လိုဝါရင့်သရုပ်ဆောင်ကြီးတွေရဲ့ နုစဉ်ဘဝကိုလတ်လတ်ဆတ်ဆတ်မြင်ရမှာဖြစ်ပါတယ်။ ပရိသတ်တွေလက်လွတ်မသင့်တဲ့ဇာတ်ကားပါ။(ဒီဇာတ်လမ်းရဲ့အညွှန်းနဲ့ ဘာသာပြန်ရေးသားပေးသူကတော့Alias ဖြစ်ပါတယ်)File Size……….(1.74 GB) / (747 MB)Quality…………WEB-DL 1080p / 720pDuration……..1Hr 38MinSubtitle………..Myanmar HardsubFormat…………MP4Genre…………..Action, Mystery, ThrillerTranslator……AliasEncoder……….SWM",
    "screenshot_links": [
      "https://image.tmdb.org/t/p/w300/uWzDaS4i4H3s4fssbFVAuFa2H57.jpg",
      "https://image.tmdb.org/t/p/w300/hBlk7XG0w4OuN3573OR91M0gqJS.jpg",
      "https://image.tmdb.org/t/p/w300/jO9cLREAKluo8GvdiXWaBMYcSgD.jpg",
      "https://image.tmdb.org/t/p/w300/oIY5Jrg1Gfg5o2tIkthP5EGD66G.jpg",
      "https://image.tmdb.org/t/p/w300/ir1TIZEUBsvKDEgcCnhKli1xAcm.jpg",
      "https://image.tmdb.org/t/p/w300/1tryXJ83oJaoIdnQVJLiZJkbpPB.jpg",
      "https://image.tmdb.org/t/p/w300/w0hpRNBo7wdeb87ozNarmqQXES1.jpg",
      "https://image.tmdb.org/t/p/w300/hcdRKY81NmW4y0qkK8c1bBEl9Cm.jpg",
      "https://image.tmdb.org/t/p/w300/mmsKzXllptAb6sgUv1KhlW7ezkP.jpg",
      "https://image.tmdb.org/t/p/w300/639oNtykbjc32ozpH6jBfg7lnKB.jpg",
      "https://image.tmdb.org/t/p/w300/3xdlUsjYLn22GkBj2t9McO5Cp1z.jpg"
    ],
    "thumbnail_link": "https://channelmyanmar.org/wp-content/uploads/2023/10/MV5BMTM5NDQyNjM1M15BMl5BanBnXkFtZTcwNDk0MzkxMQ@@._V1_FMjpg_UX1000_.jpg",
    "movie_links": [
      {
        "link": "https://yoteshinportal.cc/when-strangers-appear-2001-1080-p-web-rip-cm-mp-4",
        "server": "yoteshinportal.cc",
        "size": "1.74 GB",
        "quality": "1080p"
      },
      {
        "link": "https://megaup.net/3jQ5i/When.Strangers.Appear.2001.1080p.WEBRip.(CM).mp4",
        "server": "megaup.net",
        "size": "1.74 GB",
        "quality": "1080p"
      },
      {
        "link": "https://wishfast.top/3o1ts46wb2xl",
        "server": "streamsb.com",
        "size": "1.74 GB",
        "quality": "1080p"
      },
      {
        "link": "https://mega.nz/file/c6dzBBpQ#munY944meR2miOzGYXeIg1bOGlAZDgyRBRxGNnPppx8",
        "server": "mega.nz",
        "size": "1.74 GB",
        "quality": "1080p"
      },
      {
        "link": "https://usersdrive.com/pj5gz32wfdla.html",
        "server": "usersdrive.com",
        "size": "1.74 GB",
        "quality": "1080p"
      },
      {
        "link": "https://yoteshinportal.cc/when-strangers-appear-2001-720-p-web-rip-cm-mp-4",
        "server": "yoteshinportal.cc",
        "size": "747 MB",
        "quality": "720p"
      },
      {
        "link": "https://megaup.net/3jQ4h/When.Strangers.Appear.2001.720p.WEBRip.(CM).mp4",
        "server": "megaup.net",
        "size": "747 MB",
        "quality": "720p"
      },
      {
        "link": "https://wishfast.top/dmj8wbncw7mj",
        "server": "streamsb.com",
        "size": "747 MB",
        "quality": "720p"
      },
      {
        "link": "https://mega.nz/file/M2VFjA6Z#zL2xCS_bR0GmULagsgTcwf3VG5KqJP_UYahkUDOxyb4",
        "server": "mega.nz",
        "size": "747 MB",
        "quality": "720p"
      },
      {
        "link": "https://usersdrive.com/li73ac4ko7vx.html",
        "server": "usersdrive.com",
        "size": "747 MB",
        "quality": "720p"
      }
    ],
    "trailer": {
      "video_id": "LCHa5XZ1ixs",
      "video_url": "https://www.youtube.com/watch?v=LCHa5XZ1ixs",
      "embed_url": "https://www.youtube.com/embed/LCHa5XZ1ixs"
    }
  },
  {
    "metadata": "N/A|2001|1h 38m|Action,Comedy,Crime,Uncategorized",
    "rating": {
      "rating": "6.5/10",
      "rating_count": "1.2k"
    },
    "title": "My Boss, My Hero(2001)",
    "description": "ဂန်ဒူဆစ် ဟာ တိုက်ရည်ခိုက်ရည်ရှိပြီး လူမိုက်လောကမှာ အလားအလာကောင်းတဲ့ ဂန်းစတားတစ်ယောက်ပါသူ့ရဲ့စွမ်းဆောင်မှုတစ်ခုကြောင့် ဂိုဏ်းခေါင်းဆောင်ကြီးက သဘောကျပြီး ဆိုးလ်မြို့ရဲ့ အချက်အချာအကျဆုံးနေရာတွေထဲက တစ်ခုဖြစ်တဲ့ မြောင်ဒေါင်း ကို အုပ်ချုပ်စေဖို့ ဆုံးဖြတ်ခဲ့ပေမယ့် အထက်တန်းတောင် မအောင်တဲ့ သူ့ကိုအရေးပါတဲ့နေရာတစ်ခုကို အုပ်ချုပ်ဖို့ တာ၀န်ပေးတာ မဖြစ်သင့်ဘူးလို့ ကျန်တဲ့ လူမိုက်တွေက ဝိုင်းကန့်ကွက်ကြတဲ့အခါဂန်ဒူဆစ် တစ်ယောက် ကြီးကောင်ကြီးမား လူလတ်ပိုင်းအရွယ်ကျမှ ကျောင်းပြန်တက်ဖို့ လုပ်ရပါတော့တယ် သူ့ရဲ့တပည့်ကျော်နှစ်ယောက်ကြောင့် ပုဂ္ဂလိက ကျောင်းတစ်ခုမှာ ၀င်ခွင့်ရခဲ့ပေမယ့် ဂန်းစတားဘ၀ကနေကျောင်းသားဖြစ်သွားတဲ့ လူမိုက်ကြီး ကျောင်းမှာ ဘယ်လိုအခက်အခဲတွေနဲ့ ရင်ဆိုင်ရမလဲဆိုတာကိုဟာသလေးတွေနဲ့ ကြည့်ရှုခံစားရမှာပါဒီကားအဆက် My Boss,My Teacher (2006) ကိုhttps://channelmyanmar.org/?s=my+boss+my+teacherဒီမှာကြည့်ပါ။Translated by : Aung Tay ZaEncoded by: YKFile Size : 1.8Gb and 1.1GBQuality :: 1080p Blu-Ray 5.1CH and 720p",
    "screenshot_links": [
      "https://image.tmdb.org/t/p/w300/ovLJAwkA28f8lwLL5PqfmnkyLk1.jpg",
      "https://image.tmdb.org/t/p/w300/31GnxjgO47G2LjziUsmCGQnm2J2.jpg",
      "https://image.tmdb.org/t/p/w300/3jxWzidonBCcXYFtnHXS7lDW0E4.jpg",
      "https://image.tmdb.org/t/p/w300/vY6tiSMPLC4cYZ3jYKkIFCM15wb.jpg"
    ],
    "thumbnail_link": "https://image.tmdb.org/t/p/w185/iOyWhkeDJ7GY2VcA93KF0oLzLV6.jpg",
    "movie_links": [
      {
        "link": "https://yoteshinportal.cc/my-boss-my-hero-2001-1080-p-blu-ray-dts-x-264-cm-mp-4",
        "server": "yoteshinportal.cc",
        "size": "1.8GB",
        "quality": "1080p"
      },
      {
        "link": "https://yoteshinportal.cc/my-boss-my-hero-2001-720-p-cm-mp-4-1",
        "server": "yoteshinportal.cc",
        "size": "1.1GB",
        "quality": "720p"
      },
      {
        "link": "https://megaup.net/3Fyx4/My.Boss.My.Hero.2001.1080p.BluRay.DTS.x264(CM).mp4",
        "server": "megaup.net",
        "size": "1.8GB",
        "quality": "1080p"
      },
      {
        "link": "https://megaup.net/2ZB4i/My.Boss.My.Hero.2001.720p(CM).mp4",
        "server": "megaup.net",
        "size": "1.1GB",
        "quality": "720p"
      },
      {
        "link": "https://usersdrive.com/lm5ad4ezebhw.html",
        "server": "usersdrive.com",
        "size": "1.8GB",
        "quality": "1080p"
      },
      {
        "link": "https://usersdrive.com/3875k3lfk8al.html",
        "server": "usersdrive.com",
        "size": "1.1GB",
        "quality": "720p"
      },
      {
        "link": "https://veryfiles.com/woclpxp2yaei",
        "server": "veryfiles.com",
        "size": "1.8GB",
        "quality": "1080p"
      },
      {
        "link": "https://veryfiles.com/pbv5syh4cx5f",
        "server": "veryfiles.com",
        "size": "1.1GB",
        "quality": "720p"
      },
      {
        "link": "https://sbembed3.com/f4oabn502wba.html",
        "server": "streamsb.com",
        "size": "1.1GB",
        "quality": "720p"
      },
      {
        "link": "https://www.cmvipmembers.com/check-movies/my-boss-my-hero2001",
        "server": "VIP Links",
        "size": "1.8GB",
        "quality": "1080p"
      }
    ],
    "trailer": null
  },
  {
    "metadata": "PG-13|2001|178 min|Action,Adventure,Drama,Fantasy",
    "rating": {
      "rating": "8.8/10",
      "rating_count": "1,514,088"
    },
    "title": "The Lord of the Rings: The Fellowship of the Ring (2001)",
    "description": "The Lord of the rings နဲ့ The hobbit ရုပ်ရှင်တွေဟာ Fantasy လို့ခေါ်တဲ့ စိတ်ကူးယဉ် ရုပ်ရှင်အမျိုးအစားတွေ ဖြစ်ပါတယ်။အပြင်လောကမှာ မရှိတဲ့ ပုံပြင်တွေ ဒဏ္ဍာရီတွေ ဇာတ်ကောင်တွေနဲ့ တည်ဆောက်ထားတာပါ။ဒါပေမယ့် အချို့ Fantasy ရုပ်ရှင် စာအုပ်တွေဟာ အပြင်လောကနဲ့ ရောမွှေထားတာမျိုး ရှိတတ်ပါတယ်။ဥပမာ – နာနီယာ၊ ဟယ်ရီပေါ်တာ၊ ပါစီဂျက်ဆန် စသည်ဖြင့်ပါ။ဒါပေမယ့် ဒီ ဇာတ်လမ်းတွေကိုတော့ စာရေးဆရာကြီး J.R.R.Tolkien ကအစအဆုံး ကိုယ်ပိုင်စိတ်ကူးနဲ့ ရေးသားခဲ့တာပါ။နတ်သူငယ်တွေ၊ လူပုတွေ၊ ဘီလူးတွေရဲ့ ကိုယ်ပိုင်ဘာသာစကားကို တီထွင်ခဲ့တယ်။မူရင်းစာအုပ်တွေမှာ မြေပုံအပြည့်အစုံနဲ့ ရေးသားခဲ့တယ်။ သမိုင်းတစ်ခုလုံးကို ပြက္ခဒိန်ပါ ဖန်တီးပြီး ရေးသားခဲ့တာဖြစ်ပါတယ်။စာသားတင်မက ကဗျာတွေ သီချင်းတွေပါ ရေးဖွဲ့ခဲ့တာပါ။လူတစ်ယောက်ရဲ့ ဦးဏှောက်တစ်ခုထဲကနေ စကြဝဠာတစ်ခု ပေါ်ထွက်လာတယ်လို့ ပြောလို့ရပါတယ်။စာအုပ်ကိုအသာထားပြီး ရုပ်ရှင်အကြောင်းကိုပဲ ပြောကြပါစို့။The Lord of the rings (LotR) ရုပ်ရှင်တွေဟာ ၂၀၀၁ ကနေ စတင်ပြီးထွက်ရှိခဲ့တာဖြစ်ပါတယ်။ပထမဆုံး LotR ရုပ်ရှင် သုံးကားဟာ စုစုပေါင်း Oscar 17 ဆု ရရှိခဲ့ပါတယ်။ပထမကားက ၄ ဆု၊ ဒုတိယကားက ၂ ဆု နဲ့ သုံးကားမြောက်က ၁၁ ဆု ရရှိခဲ့တာပါ။သူ့နောက်မှ ထွက်ရှိလာတဲ့ Hobbit သုံးကားကတော့ Oscar တစ်ဆုသာ ရခဲ့ပါတယ်။LotR ရုပ်ရှင်တွေရဲ့ အောင်မြင်မှုဟာ ကာလအကန့်အသတ်မရှိ timeless လို့ပဲ ပြောရမှာဖြစ်ပါတယ်။၂၀၀၁ တုန်းက လူတွေကြိုက်ခဲ့သလို ၃၀၀၁ ခုနှစ်မှာလည်း ကြိုက်ကြဦးမှာပါပဲ။အဓိကကတော့ ဇာတ်လမ်းအတွက် ဝတ်စုံ၊ရိုက်ကွင်းပြင်ဆင်မှုတွေ၊ ရိုက်ချက်တွေ၊ သရုပ်ဆောင်တွေ အသေးစိတ်ကျခဲ့တယ်၊ ခမ်းနားခဲ့တယ်လို့ပြောရမှာပါပဲ။နောက်ထပ် ချီးကျူးရမှာကတော့ ဇာတ်ညွှန်းပါ။ စာအုပ်ပါ ဖတ်ဖူးတဲ့သူတွေ ပိုသိပါလိမ့်မယ်။အရမ်းကိုကောင်းတဲ့ ဝတ္ထုရှည်ကြီးတစ်ခုကို ကြည့်လို့လည်းကောင်းအောင် အခန်းတွေဖြတ်တောက်ရ၊ ဇာတ်ကောင်တွေ ဖယ်ထုတ်ရတာ မလွယ်လှပါဘူး။ဒါပေမယ့် အကောင်းဆုံး လုပ်နိုင်ခဲ့ပါတယ်။ ဒိုင်ယာလော့တွေ ဇာတ်လမ်းအနိမ့်အမြင့်တွေကိုလည်း အရှိန်တင်ပေးသွားတာ အံ့သြလောက်ပါတယ်။ဥပမာ – လက်စွပ်ကို ဖျက်ဆီးဖို့ ဆွေးနွေးကြတဲ့အခန်းမှာ ဝတ္ထုအတိုင်းဆို အယ်ရွန်က အားလုံးကို ကြိုတင်မိတ်ဆက်၊ သမိုင်းကို ပြောပြပြီးမှ စတင်ဆွေးနွေးကြတာဖြစ်ပါတယ်။ဇာတ်လမ်းထဲမှာတော့ ဒီအတိုင်း ဆွေးနွေးကြရင်း ဘိုမီရာက အာရာဂွန်ကို အထင်သေးစကားပြောချိန်မှာလီဂိုးလက်စ်က ထပြောလိုက်တဲ့အခန်းမျိုး ပြင်လိုက်ခြင်းအားဖြင့် ဇာတ်ရှိန် တက်သွားတာ ရှိပါတယ်။ပြီးတော့ အာရာဂွန်ဟာ ထီးနန်းကို ဆက်တိုက်ငြင်းပယ်ခဲ့တာ၊ Andúril ဓားကို နောက်ဆုံးအချိန်မှ ပြန်ပြင်တာတွေဟာ ဇာတ်ရှိန်ပိုတက်စေတဲ့ ပညာပါပဲ။ပြီးတော့ ဆာရူးမန်းကို သေခိုင်းတဲ့ ဇာတ်ညွှန်းမျိုးဟာ အတော်လေးကို ရဲတင်းရာကျပါတယ်၊ဘာကြောင့်လဲ ဆိုတော့ စာအုပ်ထဲမှာ ဆာရူးမန်းဟာ ထွက်ပြေးသွားခဲ့ပါတယ်။လက်စွပ်ကိုဖျက်ဆီးပြီးလို့ ဟော့ဘစ်တွေ ရှိုင်းယားကို ပြန်လာချိန်မှာ ဆာရူးမန်းနဲ့ ထပ်ပြီးရင်ဆိုင်ကြရပါသေးတယ်။ဒါတွေကို ဖျက်ပစ်လိုက်ပေမယ့် ရုပ်ရှင်က ညံ့မသွားခဲ့တာကို တွေ့မှာပါ။ဒါကတော့ ဇာတ်ညွှန်းဆရာတွေရဲ့ အရည်အချင်းတွေပါပဲ။၁ မျက်နှာ ဖန်တရာတေ ဇာတ်ညွှန်းဆရာတွေ လေ့လာသင့်ပါတယ်။ဇာတ်လမ်းအကျဉ်း===========Three Rings for the Elven-kings under the sky,Seven for the Dwarf-lords in their halls of stone,Nine for Mortal Men doomed to die,One for the Dark Lord on his dark throneIn the Land of Mordor where the Shadows lie.One Ring to rule them all, One Ring to find them,One Ring to bring them all, and in the darkness bind them,In the Land of Mordor where the Shadows lie.ဒါကတော့ LotR ဇာတ်လမ်းကြီးကို စတင်ခဲ့တဲ့ ဂန္ဓဝင်ကဗျာကြီးပါပဲ။Dark Lord ဆော်ရွန်ဟာ နတ်သူငယ်တွေအတွက် လက်စွပ် ၃ ကွင်း၊ လူပု ဘုရင် ၇ ပါးအတွက် လက်စွပ် ၇ ကွင်း၊ လူတွေအတွက် ၉ ကွင်းကို ထုလုပ်စေခဲ့ပြီး ပေးအပ်ခဲ့ပါတယ်။လက်စွပ်ကိုယ်စီဟာ စွမ်းအားရှိတာမို့ သူတို့တွေ လက်ခံခဲ့ကြတယ်။ဒါပေမယ့် ဆော်ရွန်ဟာ လက်စွပ်ရှင်အားလုံးကို လွှမ်းမိုးနိုင်တဲ့ လက်စွပ်အားလုံးရဲ့ ဘုရင် တစ်ခုတည်းသော လက်စွပ်ကို ထုလုပ်ခဲ့ပြီး အားလုံးကိုချုပ်ကိုင်ဖို့ ကြိုးစားပါတော့တယ်။ဒါပေမယ့် မဟာမိတ်တွေနဲ့ နောက်ဆုံးစစ်ပွဲမှာ ရှုံးနိမ်ခဲ့ပြီး လက်စွပ်ကိုလည်းလက်လွှတ်လိုက်ရပါတယ်။နှစ်ပေါင်းများစွာကြာပြီးနောက် လက်စွပ်ပြန်ပေါ်လာချိန် ဆော်ရွန်လည်းအင်အားကြီးလာချိန်မှာနတ်သူငယ်တွေ၊ လူတွေ၊ လူပုတွေ၊ ဟော့ဘစ်လေးတွေဟာ ဆော်ရွန်ကို တားဆီးဖို့နဲ့ လက်စွပ်ဖို့ ဖျက်ဆီးဖို့ ကြိုးစားကြရပါတော့တယ်……….ဒီလောက်ဆို ဒီရုပ်ရှင်တွေကို ဆက်ပြီးခံစားဖို့ လုံလောက်မှာပါ။LotR ဇာတ်လမ်းမှာ အရေးပါခဲ့တဲ့ ကဗျာတစ်ခုကိုလည်း ဖော်ပြပေးလိုက်ပါတယ်။All that is gold does not glitterNot all those who wander are lost;The old that is strong does not wither,Deep roots are not reached by the frost.From the ashes, a fire shall be woken,A light from the shadows shall spring;Renewed shall be blade that was broken,The crownless again shall be kingရွှေအဆင်းအတိနဲ့အရာဟာ တစ်လက်လက် တောက်ပမနေတတ်ပါဘူးလှည့်လည်နေသူတိုင်းဟာလည်း လမ်းပျောက်နေကြတာမဟုတ်ပါအိုမင်းပေမယ့် ကြံ့ခိုင်သူဟာ ဆွေးမြေ့မလာတတ်ပါနက်ရှိုင်းလွန်းတဲ့ အမြစ်တွေဟာ သစ်တောနဲ့ အလှမ်းကွာစမြဲပြာပုံကြားကနေ မီးတောက်နိုးထလာချိန်အမှောင်တွေထဲက အလင်းတန်းတစ်ခု ဖြန်းပက်လာရင်းကျိုးပဲ့သွားခဲ့တဲ့ဓားကို ပြန်လည်ပြုပြင်ပြီးချိန်မှာသရဖူမဲ့နေခဲ့သူဟာ ဘုရင်ပြန်လည်ဖြစ်လာမှာပါ။(1) The Fellowship of The Ring(အော်စကာ ဆန်ကာတင် ၁၃ နေရာရရှိပြီး အော်စကာ ၄ဆု ရရှိခဲ့)(မူရင်းရုပ်ရှင်ဗားရှင်းမှာ ၃နာရီ ကြာမြင့်ပြီး လက်ရှိ Extended Versionမှာ ၃ နာရီခွဲ ကြာမြင့်)(2) The Two Towers (အော်စကာ ဆန်ကာတင် ၆ နေရာရရှိပြီး ၂ ဆု ရရှိခဲ့)(မူလဗားရှင်းမှာ ၃ နာရီကြာမြင့်ပြီး Ext.version မှာ ၃ နာရီ ၄၀ မိနစ် ကြာမြင့်)(3) The Return of The King (အော်စကာ ဆန်ကာတင် ၁၁ နေရာရရှိခဲ့ရာတွင် ၁၁ ဆုလုံးအား စံချိန်တင်ရရှိသွားခဲ့)(မူလဗားရှင်းမှာ ၃ နာရီ မိနစ် ၂၀ ဖြစ်ပြီး ext.version မှာ ၄ နာရီ ၁၁ မိနစ်ကြာမြင့်)The Lord of the Rings ဟာ ရုပ်ရှင်သမိုင်းရဲ့ အကြီးကျယ်ဆုံး အအောင်မြင်ဆုံးရုပ်ရှင်တွေထဲက တစ်ခုဖြစ်ပါတယ်။အောင်မြင်မှုတွေကိုကတော့ တွေ့တဲ့အတိုင်းဖြစ်ပြီး RT မှာ rating 90% အထက် IMDb မှာ 8 အထက်တွေချည်းပဲဖြစ်ပါတယ်။ကျွန်တော်တို့ ငယ်ငယ်ကတည်းက ခဏဏကြည့်ခဲ့ရပေမယ့် Thea.version နဲ့ Extended Version ၂ ခုလုံးကိုတော့ လူတိုင်းကြည့်ဖြစ်မယ်မထင်သေးပါဘူး။တကယ်လို့ မိတ်ဆွေဟာ LOTR ကို ၉နာရီအစအဆုံးပဲ runကြည့်ဖူးတယ်ဆိုမပြည့်စုံသေးဘူးလို့ ပြောလိုက်ပါရစေ။တစ်ခေါက်လောက် ၁၂ နာရီ ဗားရှင်းလေး runကြည့်ဖို့ ဖိတ်ခေါ်လိုက်ပါတယ်။File size…(8.1 GB) and (3.4 GB)Quality….Extended BluRay4K HDR& 1080p HEVCFormat…mkvDuration….03:48:18Subtitle….Myanmar Subtitle (Hardsub)Encoder….Nyeinsaeya AungTranslated byDr.Nyan",
    "screenshot_links": [
      "https://image.tmdb.org/t/p/w300/vRQnzOn4HjIMX4LBq9nHhFXbsSu.jpg",
      "https://image.tmdb.org/t/p/w300/keyOZ8KcjHMTVH8p0owTXvw18Wf.jpg",
      "https://image.tmdb.org/t/p/w300/a0lfia8tk8ifkrve0Tn8wkISUvs.jpg",
      "https://image.tmdb.org/t/p/w300/tdmlSbLl84hfHx635AqHLB8Qh8M.jpg",
      "https://image.tmdb.org/t/p/w300/gU84vBGG2x8K3x1zrz4SggiN5hr.jpg",
      "https://image.tmdb.org/t/p/w300/mWDdRXTivGE7aaY2vo1Ie0PfCX5.jpg",
      "https://image.tmdb.org/t/p/w300/ua5EHfleb44L5hfHPs2BPqRAove.jpg",
      "https://image.tmdb.org/t/p/w300/dUVbWINfRMGojGZRcO6GF1Z2nV8.jpg",
      "https://image.tmdb.org/t/p/w300/skVTWsoQvFGLUnOo1Wv3coAsARw.jpg",
      "https://image.tmdb.org/t/p/w300/oiwc338EoBgS4sEI2ixAny4KQKg.jpg",
      "https://image.tmdb.org/t/p/w300/tqj7NKj11keFuLzPsBDMUq2dOUO.jpg",
      "https://image.tmdb.org/t/p/w300/9ilNwwf9YzDV2lNJ3JUKGgXvHP7.jpg",
      "https://image.tmdb.org/t/p/w300/6iHH1EsNYzk9azv6H9xOQZQE458.jpg",
      "https://image.tmdb.org/t/p/w300/x4NZ2JSb8ojOK0NPOScagYn6sQK.jpg",
      "https://image.tmdb.org/t/p/w300/ssKTgmA1S7GLiPe83tVoitk7Nqd.jpg",
      "https://image.tmdb.org/t/p/w300/LEuEcERF2n455qHZodqYp75m3f.jpg",
      "https://image.tmdb.org/t/p/w300/29t27rSQel2Ao8I7OwUkUF66RVB.jpg",
      "https://image.tmdb.org/t/p/w300/lqfPg1CAJezp3iwtQghl0skDwbm.jpg",
      "https://image.tmdb.org/t/p/w300/duxXmVTVe9JzwDvRMY2vDZlC6aB.jpg",
      "https://image.tmdb.org/t/p/w300/ftrUMC7yFGTFUsG1JBbfuSKAkDH.jpg",
      "https://image.tmdb.org/t/p/w300/zzIdXP769uYxQq6rK9plfeoVdTo.jpg",
      "https://image.tmdb.org/t/p/w300/3wiSgRRKokK660O75vJAGmk7FWF.jpg",
      "https://image.tmdb.org/t/p/w300/jY0MmuyuIeuh2NdhbEBALmTjxkq.jpg",
      "https://image.tmdb.org/t/p/w300/2FkBCRES38QATPehkDSJKJ0QrXJ.jpg",
      "https://image.tmdb.org/t/p/w300/45mrNIMqy2ztrA0vTmZzd3nIcIq.jpg",
      "https://image.tmdb.org/t/p/w300/v2R6n5vplRDoeUBlzQdCIP8dof4.jpg",
      "https://image.tmdb.org/t/p/w300/zg2ml7qvKCt0ap1wTu1N1XknLz7.jpg",
      "https://image.tmdb.org/t/p/w300/rc2q7bYU9al5rpvyOO6wHZswlFD.jpg"
    ],
    "thumbnail_link": "https://image.tmdb.org/t/p/w185/6oom5QYQ2yQTMJIbnvbkBL9cHo6.jpg",
    "movie_links": [
      {
        "link": "https://www.cmvipmembers.com/check-movies/the-lord-of-the-rings-the-fellowship-of-the-ring-2001",
        "server": "VIP Links",
        "size": "",
        "quality": ""
      },
      {
        "link": "https://yoteshinportal.cc/cm-hdr-lord-of-the-rings-the-fellowship-of-the-ring-2001-extended-2160-p-4-k-hdr-10-bit-blu-ray-x-265-hevc-aac-5-1-nyein-mkv",
        "server": "yoteshinportal.cc",
        "size": "8.1 GB",
        "quality": "4K HDR HEVC"
      },
      {
        "link": "https://mega.nz/file/s01yTILA#6XvktXlrWu7V3qvyrnbvIru__U_3iP6Xm0YWfK1zgBM",
        "server": "mega.nz",
        "size": "8.1 GB",
        "quality": "4K HDR HEVC"
      },
      {
        "link": "https://usersdrive.com/jb4d4toril3g.html",
        "server": "usersdrive.com",
        "size": "8.1 GB",
        "quality": "4K HDR HEVC"
      },
      {
        "link": "https://yoteshinportal.cc/cm-lord-of-the-rings-the-fellowship-of-the-ring-2001-extended-1080-p-blu-ray-x-265-hevc-aac-5-1-nyein-mkv",
        "server": "yoteshinportal.cc",
        "size": "3.4 GB",
        "quality": "1080p HEVC"
      },
      {
        "link": "https://megaup.net/12kto/(CM)Lord-of-the-Rings-The-Fellowship-of-the-Ring-2001-EXTENDED-1080p-BluRay-x265-HEVC-AAC-5.1-Nyein.mkv",
        "server": "megaup.net",
        "size": "3.4 GB",
        "quality": "1080p HEVC"
      },
      {
        "link": "https://mega.nz/file/Jg0EhSjA#eFU-kFSyplVC9q_8cTun9TbgsO_02ySHIlQApMXQnD8",
        "server": "mega.nz",
        "size": "3.4 GB",
        "quality": "1080p HEVC"
      },
      {
        "link": "https://usersdrive.com/se3eetcznaan.html",
        "server": "usersdrive.com",
        "size": "3.4 GB",
        "quality": "1080p HEVC"
      },
      {
        "link": "https://viewsb.com/iw4flztkmtye.html",
        "server": "streamsb.com",
        "size": "3.4 GB",
        "quality": "1080p HEVC"
      }
    ],
    "trailer": {
      "video_id": "7HbDcTw7E2g",
      "video_url": "https://www.youtube.com/watch?v=7HbDcTw7E2g",
      "embed_url": "https://www.youtube.com/embed/7HbDcTw7E2g"
    }
  },
  {
    "metadata": "R|2001||Drama,Thriller",
    "rating": {
      "rating": "6.4/10",
      "rating_count": ""
    },
    "title": "Along Came a Spider (2001)",
    "description": "မင်းသားကြီး မော်ဂန် ဖရီးမန်း ပါဝင်သရုပ်ဆောင်ထားပြီး2001 တုန်းကထွက်ရှိခဲ့တဲ့ မှုခင်းအက်ရှင်‌ကားကောင်းတစ်ကားကိုတင်ဆက်ပေးလိုက်ပါတယ်။ဇာတ်လမ်းအကျဉ်းကတော့ စိတ်ပညာရှင်/စုံထောက်ဒေါက်တာ အဲလက်စ် ခရော့စ် (မော်ဂန် ဖရီးမန်း) ဟာစစ်ဆင်ရေးတစ်ခုမှာ သူ့ရဲ့တွဲဖက်ကို ဆုံးရှုံးလိုက်ရပြီးကတည်းကသူ့ကိုယ်သူခွင့်မလွှတ်နိုင်ပဲ၊ ဘဝကြီးကိုလည်းရည်ရွယ်ချက်မရှိဖြတ်သန်း‌နေသူပါ။ဒီဖြစ်ရပ်ဆိုးကြီး ဖြစ်အပြီး ရှစ်လအကြာမှာတော့ပြည်နယ်လွှတ်တော်အမတ် ဟန့်ခ် ရို့စ်ရဲ့ကိုယ်ပိုင်ကျောင်းတစ်ခုမှာကျောင်းတက်နေတဲ့သမီးလေး ရို့စ်ဟာ Secret Service ရဲ့စောင့်ရှောက်မှုအောက်မှာရှိနေရင်းနဲ့ ပြန်ပေးဆွဲခံလိုက်ရပါတယ်။ဒီလိုနဲ့ အဲလက်စ်ဆီကို ပြန်ပေးသမားကဖုန်းဆက်ပြီးသူရဲ့ကစားပွဲထဲကို ဝင်ပါခိုင်းရင်း အဲလက်စ်တစ်ယောက် ပြန်ပေးသမားရဲ့ကစားပွဲကိုနိုင်အောင်ကစားနိုင်မှာလား၊ ရို့စ်ကိုရော အောင်အောင်မြင်မြင်နဲ့ကယ်ထုတ်နိုင်မှာလား၊ဘယ်လိုအန္တရာယ်တွေကိုရင်ဆိုင်ရမလဲ၊ဘယ်လိုအလှည့်အပြောင်းတွေရှိလာမလဲဆိုတာကိုတော့ဆက်လက်ကြည့်ရှုပေးကြပါဦးဗျ။File size…  2.77 GB /  742 MBQuality… Blu-Ray 1080p / 720pFormat… mp4Duration…. 1h 39mGenre …..  Drama , ThrillerSubtitle…. Myanmar Subtitle (Hard Sub)Encoder…. Min WaiTranslated by TMMT",
    "screenshot_links": [
      "https://image.tmdb.org/t/p/w300/5C6njaciKvyZlKWUrQX7mjdl4D1.jpg",
      "https://image.tmdb.org/t/p/w300/zKSWokNYMgI1skePqrN1C00Lmm6.jpg",
      "https://image.tmdb.org/t/p/w300/3LRjM5M5WidHKlRQuSvqRwU2Fjr.jpg",
      "https://image.tmdb.org/t/p/w300/4MrSQ53Bz0iEo1hITjj5NmFwPY2.jpg",
      "https://image.tmdb.org/t/p/w300/kHiZahUzDLVeCQJqswtkVl1Gbod.jpg",
      "https://image.tmdb.org/t/p/w300/asbxgWlg9mqiAUMtmOJHEX3wbhB.jpg",
      "https://image.tmdb.org/t/p/w300/3qF1ngwnnyYE06HmWpp2c3fKdlc.jpg",
      "https://image.tmdb.org/t/p/w300/7V3P7WSrGOiQg1k3NcMjK6Nr0af.jpg",
      "https://image.tmdb.org/t/p/w300/sayWwgXgfPPacTMyhwaXvOjOcCc.jpg",
      "https://image.tmdb.org/t/p/w300/hk0ORvoRYmYJH9nv2xkOOIequIl.jpg"
    ],
    "thumbnail_link": "https://image.tmdb.org/t/p/w185/1YtsND7vSNymylnOSzgg3DdVFMB.jpg",
    "movie_links": [
      {
        "link": "https://usersdrive.com/mrc4sp0k3jiz.html",
        "server": "usersdrive.com",
        "size": "742 MB",
        "quality": "720P"
      },
      {
        "link": "https://megaup.net/1Tu2f/Along.Came.a.Spider.2001.720p.Encode.mp4",
        "server": "megaup.net",
        "size": "742 MB",
        "quality": "720P"
      },
      {
        "link": "https://lvturbo.com/edh68p1oppfb.html",
        "server": "streamsb.com",
        "size": "742 MB",
        "quality": "720P"
      },
      {
        "link": "https://streamvid.net/3t02jg15mp4f",
        "server": "streamvid.io",
        "size": "742 MB",
        "quality": "720P"
      },
      {
        "link": "https://usersdrive.com/23rjqyeecstt.html",
        "server": "usersdrive.com",
        "size": "2.77 GB",
        "quality": "1080P"
      },
      {
        "link": "https://megaup.net/1dwyv/Along.Came.a.Spider.2001.1080p.Encode.mp4",
        "server": "megaup.net",
        "size": "2.77 GB",
        "quality": "1080P"
      },
      {
        "link": "https://lvturbo.com/ll51v42cjvlx.html",
        "server": "streamsb.com",
        "size": "2.77 GB",
        "quality": "1080P"
      },
      {
        "link": "https://streamvid.net/3t02jg15mp4f",
        "server": "streamvid.io",
        "size": "2.77 GB",
        "quality": "1080P"
      }
    ],
    "trailer": {
      "video_id": "kswRbwYqn3k",
      "video_url": "https://www.youtube.com/watch?v=kswRbwYqn3k",
      "embed_url": "https://www.youtube.com/embed/kswRbwYqn3k"
    }
  },
  {
    "metadata": "PG|2001|1h 50min|Comedy",
    "rating": {
      "rating": "4.8/10",
      "rating_count": "2,462"
    },
    "title": "Mr. Bones (2001)",
    "description": "Mr. Bones (2001)_____IMDb – 4.8/1090’s Born တွေတော်တော်များများ နဲ့ရင်းနှီးကြတဲ့ ဟိုး ဗီဒီယိုတိတ် နဲ့ ခေတ်ကထဲ ကဂျီးကပ် မှိုတတ်နေတဲ့အခွေကို ဘာသာစကားနားမလည်ပဲကြည့်တာတောင် အူတက်မတတ် ခွီခဲ့ရတဲ့အာဖရိက ရောက်လူဖြူကြီး Mr. Bone ရဲ့မင်းသားရှာပုံတော် ခရီးကို တင်ဆက်ပေးလိုက်ပါတယ်ဇာတ်ကားက Comedy မှာ စွန်း ဖောက်တဲ့ ကားမို့ဇာတ်ကြောင်းအထွေအထူးပြောစရာမလိုဘူးလို့ထင်မိပါတယ်ဒီကားကို ဒါရိုက်တာ Gray Hofmeyr က ရိုက်ကူးထားပြီးGoogle ကိုခေါက်ကျိမယ်ဆိုရင် ၉၇% သောသူတွေကဒီကားကို ကြိုက်နှစ်သက်ကြပါတယ်တဲ့ဗျာကဲ သင်္ကြန်ပိတ်ရက်မှာ ဒီဟာသကားလေးကိုကြည့် စိတ်အမောတွေဖြေဖျောက်ပြီးနှစ်သစ်ကို ပျော်ရွှင်စွာနဲ့ ဖြတ်သန်းလိုက်ကြရအောင်လားဗျာTranslator က မမဖြူသန့်ဖြစ်ပြီးတော့Encoder ကတော့ Kyaw Ye Aung ပါ",
    "screenshot_links": [],
    "thumbnail_link": "https://channelmyanmar.org/wp-content/uploads/2018/04/mr.-bones-poster.jpg",
    "movie_links": [
      {
        "link": "https://usersdrive.com/1wm11496rxnn.html",
        "server": "usersdrive.com",
        "size": "695 MB",
        "quality": ""
      },
      {
        "link": "https://yoteshinportal.cc/mr-bones-2001-mm-sub-mp-4",
        "server": "yoteshinportal.cc",
        "size": "695 MB",
        "quality": ""
      },
      {
        "link": "https://yuudrive.me/9609da5/mr-bones-201-m-sub-mp4",
        "server": "yuudrive.me",
        "size": "695 MB",
        "quality": ""
      },
      {
        "link": "http://www.filedwon.info/qbfp54nzwxno/Mr._Bones_[2001]_(MM_Sub).mp4.html",
        "server": "filedwon.info",
        "size": "695 MB",
        "quality": ""
      },
      {
        "link": "https://megaup.net/2fsJ0/Mr._Bones_[2001]_(MM_Sub).mp4",
        "server": "megaup.net",
        "size": "695 MB",
        "quality": ""
      },
      {
        "link": "https://mega.nz/file/x9hSBJ7S#aIH1-mTHS6uuvEvvkNUO8iwLEJ6nNkW5KAR2vT7HQQA",
        "server": "mega.nz",
        "size": "695 MB",
        "quality": ""
      },
      {
        "link": "https://upstream.to/a4zwgbgf0vba",
        "server": "upstream.to",
        "size": "695 MB",
        "quality": ""
      }
    ],
    "trailer": {
      "video_id": "br0cyOHUi4A",
      "video_url": "https://www.youtube.com/watch?v=br0cyOHUi4A",
      "embed_url": "https://www.youtube.com/embed/br0cyOHUi4A"
    }
  },
  {
    "metadata": "N/A|2001|106 min|Asian,War",
    "rating": {
      "rating": "7.1/10",
      "rating_count": "354"
    },
    "title": "Purple Sunset (2001)",
    "description": "ဒီဇတ္လမ္းကို ၾကည့္ဖူးတဲ့သူေတြကေတာ့ ၾကည့္ဖူးတယ္ေသခ်ာသေလာက္ကေတာ့ အဲ့ဒီလူေတြ အသက္ ၃၀ ေလာက္ ရွိေလာက္ၿပီရုပ္ရွင္ကားကို ဒုတိယ ကမၻာစစ္ ေလာက္မွာ အေျခတည္ထားၿပီးအဓိက ဇတ္ေကာင္ ၃ ေယာက္ နဲ႔ ရင္သက္ရႈေမာဖြယ္ျဖစ္ေအာင္ရိုက္ျပသြားႏုိင္တဲ့ ရုပ္ရွင္ကားပါ…ဂ်ပန္ေတြဟာ တရုတ္ျပည္တြင္းမွာ အေျခတည္ေနတဲ့ အခ်ိန္တရုတ္လူမ်ိဳးေတြကို ႏွိပ္စက္ ၊ သားမယားျပဳက်င့္ ၊ သက္ျဖတ္သလိုဂ်ပန္လူမ်ိဳးေတြကိုပါ ေခၚလာၿပီး ရြာတည္ေနခဲ့ပါတယ္…အဲ့ဒီလိုအခ်ိန္မွာပဲ ရုရွားစစ္တပ္ ကလဲ ဂ်ပန္ေတြကို ၀င္တုိက္ပါတယ္တရုတ္ရြာသားေလး တစ္ေယာက္ဟာ စစ္သံု႔ပန္းအျဖစ္အဖမ္းခံရၿပီး သတ္ခံရ စဲစဲ မွာပဲ ရုရွားတပ္ေတြ ၀င္ကယ္လို႔ရုရွားေတြ နဲ႔ အတူ ခရီးဆက္တဲ့ အထဲ ပါသြားပါတယ္…နယ္ေျမ မကၽြမ္းတဲ့ ရုရွားေတြကလဲ ေယာင္ေတာင္ေတာင္ နဲ႔တရုတ္နယ္ေျမထဲ ရြာတည္ထားတဲ့ ဂ်ပန္ေတြဆီကိုဆိုက္ဆုိက္ၿမိဳက္ၿမိဳက္ကို ေရာက္သြားတာပါပဲပစ္ၾကခတ္ၾက ေသၾက ရင္း တစ္ရြာလံုး ထြက္ေျပးၾကတယ္အဲ့ဒီရြာမွာပဲ ဂ်ပန္ေက်ာင္းသူေလး ၁ ေယာက္အသက္ရွင္က်န္ခဲ့သလို ရုရွားအဖြဲ႔လဲ လူေတြ ကြဲသြားၿပီးတရုတ္ေကာင္ေလး နဲ႔ ရုရွားဗိုလ္အမ်ိဳးသမီး ကဂ်ပန္မေလးကို ဖမ္းၿပီး အိမ္ျပန္လမ္းကို ျပခိုင္းေတာ့တာပါပဲလူမ်ိဳး မတူ ဘာသာမတူ စကားနားမလည္တဲ့ ၃ ေယာက္ေတာထဲမွာ ခရီးတူတူ ဆက္ၾကတာဟာၾကည့္ရႈသူကို ရသမ်ိဳးစံု ခံစားရေစပါတယ္ဒီကားကို Sane Khet က ဘာသာျပန္ေပးထားၿပီးShwe Sin Nan Eain မွ အညႊန္းေရး တင္ဆက္ထားပါတယ္(တိပ္ေခြေခတ္က ရုပ္ထြက္ျဖစ္တဲ့အတြက္Quality DVDrip ခန္႔သာ ရွိလို႔ ဖုန္းႏွင့္သာ ၾကည့္ရႈၾကပါရန္)",
    "screenshot_links": [],
    "thumbnail_link": "https://channelmyanmar.org/wp-content/uploads/2019/03/MV5BMWY4NDFiZGEtMjE4Zi00YzM0LThjNTAtNzFiNDQ0OGY3MGIwXkEyXkFqcGdeQXVyMjExMzEyNTM@._V1_.jpg",
    "movie_links": [
      {
        "link": "https://upstream.to/dazf96186oed",
        "server": "upstream.to",
        "size": "720 MB",
        "quality": "DVD Rip"
      },
      {
        "link": "https://megaup.net/2e6rh/Purple_Sunset_(Ziri)_[2001]_(MM_Sub).mp4",
        "server": "megaup.net",
        "size": "720 MB",
        "quality": "DVD Rip"
      },
      {
        "link": "https://usersdrive.com/1dka59lii2ug.html",
        "server": "usersdrive.com",
        "size": "720 MB",
        "quality": "DVD Rip"
      }
    ],
    "trailer": null
  },
  {
    "metadata": "Unrated|2001|1h 40m|Adult,Drama",
    "rating": {
      "rating": "5.2/10",
      "rating_count": "30"
    },
    "title": "[18+] Love Her (2001)",
    "description": "Love Her (2001)(ကိုရီးယား Adult ကားတွေထုံးစံအတိုင်း 1080p ရဖို့မလွယ်လို့ 480p ကိုပဲ ကြည့်လို့‌ပြေအောင် ကုတ်တင်ပေးလိုက်ပါတယ်ခင်ဗျာ)ညနေရီ ပန်းခင်းထဲက လွင့်သွားတဲ့ လေပြေမှာ သူမရဲ့ ဝတ်ရုံအနီဟာ လွင့်ဝဲနေတယ်။ ကျွန်တော်ကလည်း သက်ငြိမ်ငေးမောလို့။ ဟိုးအဝေးဆီမှာ လှေကလေးတစ်စင်း နေဝင်ရီကောင်းကင်အောက် မျောပါနေတာကိုလည်း ကျွန်တော်မြင်ရတယ်။ လှေငယ်လေး ပျောက်ကွယ်သွားတဲ့အချိန် သူမရဲ့ လေနှင်ရာမျောလွင့်နေတဲ့ ဝတ်ရုံအနီလေးကို ကျွန်တော်လည်ပြန်ကြည့်မိပေမဲ့ ဝတ်ရုံအနီလေးမရှိတော့ဘူး။ သူမလည်း မရှိတော့။ တကယ်ဆို သူမရှိတော့တာ ကြာခဲ့ပြီ။ ဒါတွေဟာ ကျွန်တော့်ရဲ့ထင်ယောင်ထင်မှားတွေလို့ တွေးမိချိန်မှာ မျက်ရည်ဟာ တဖြိုင်ဖြိုင်ကျတော့တာပါပဲ။သူမဟာ တေးရေးဆရာဖြစ်ချင်ခဲ့တဲ့ ကျွန်တော့်ရဲ့ မအောင်မြင်ခဲ့တဲ့ အတိတ်တွေမှာ အိပ်မက်တွေလဲပြိုမသွားအောင် ခိုင်မာပေးခဲ့တဲ့ ကျောက်ဆောင်တစ်ခုလိုပေါ့။ ကျွန်တော်ကတော့ သူမရဲ့ အိပ်မက်တွေကို တတိတိတိုက်စားခဲ့တဲ့ ဒီလှိုင်းတစ်ခုပေါ့။ ဝေသာလီဗျိုင်းမျိုးနဲ့ ယမုံနာရွှေငါးလေးဘဝကွာမည်ဆိုလည်း တစ်ကမ္ဘာကွာဝေးရော။ ဒီလိုနဲ့ ကျွန်တော့်ရဲ့ မအောင်မြင်ခြင်းတွေ သူမကို တတိတိလှိုက်စား ကျွန်တော့်အိပ်မက်တွေအတွက် ခိုင်မာပေးခဲ့တဲ့ ကျောက်ဆောင်ဟာ သူ့အတွက်သူမှာတော့ ပြိုလဲသွားခဲ့တယ်။သူမ ပြောဖူးတယ်။ ကလေးလေးတွေဟာ အိပ်မက်တွေကို လက်သီးဆုပ်ထဲထည့်ပြီး လောကထဲ လက်သီးဆုပ်ပြီး ရောက်လာကြတယ်တဲ့။ မွေးလာပြီးလို့ အဲဒီလက်သီးဆုပ်ကလေးတွေကို ဖြန့်လိုက်တဲ့အခါ အိပ်မက်တွေ လွတ်ထွက်သွားပြီး တစ်ဘဝလုံး အိပ်မက်တွေနောက် လိုက်ရတော့တယ်တဲ့။ တစ်ခါတလေ ကျွန်တော်တွေးမိတယ်။ ကျွန်တော့်လက်သီးဆုပ်ထဲက အိပ်မက်ကလေးဟာ ဘာများပါလဲလို့ပေါ့။ အချိန်တွေနှောင်းမှ သိလိုက်ရတာက ကျွန်တော့်လက်သီးဆုပ်ထဲက အိပ်မက်ကလေးဟာ သူမပါပဲ။ ဒါပေမဲ့ အဲဒီဝတ်ရုံအနီလေးက နေဝင်ချိန်နေမင်းကြီးထဲ ပျောက်ပျက်သွားခဲ့ပြီ။(ဒီဇာတ်ကားနဲ့အညွှန်းကို “___” မှ ပြန်ဆို ရေးသားထားပါတယ်)Size – 1.42GBQuality – 1080p, 720pIMDb Rating – 5.2/10Format – mp4Duration – 1H 40MinGenre – Adult, DramaSubtitle – Myanmar Subtitle (Hardsub)Translated by “___“Encoded byRGB",
    "screenshot_links": [],
    "thumbnail_link": "https://image.tmdb.org/t/p/w185/dP16pI7PTO9MFHFV85nWwjNXb9A.jpg",
    "movie_links": [
      {
        "link": "https://yoteshinportal.cc/cm-love-her-2001-480-p-mp-4",
        "server": "yoteshinportal.cc",
        "size": "1.42GB",
        "quality": "1080p"
      },
      {
        "link": "https://megaup.net/18N4z/(CM)_Love_Her_(2001)_480p.mp4",
        "server": "megaup.net",
        "size": "1.42GB",
        "quality": "1080p"
      },
      {
        "link": "https://mega.nz/file/G4oGHCZJ#ipQCZYbBLWkYu_OHSOSBfHST3YC_QoB1DoY0Wokq07o",
        "server": "mega.nz",
        "size": "1.42GB",
        "quality": "1080p"
      },
      {
        "link": "https://usersdrive.com/u10q5vqyqf1x.html",
        "server": "usersdrive.com",
        "size": "1.42GB",
        "quality": "1080p"
      },
      {
        "link": "https://sblanh.com/x1yfacqijap3.html",
        "server": "streamsb.com",
        "size": "1.42GB",
        "quality": "1080p"
      }
    ],
    "trailer": null
  },
  {
    "metadata": "R|2001|1h 26m|Drama,Romance",
    "rating": {
      "rating": "7.1/10",
      "rating_count": "2.4K"
    },
    "title": "Lan Yu (2001)",
    "description": "Lan Yu (2001)Demi gods and Semi Devils, Sword Snow Stride (2021) တို့မှာ လူကြိုက်များပြီး နာမည်ကြီးခဲ့တဲ့ မင်းသားကြီး Hu Jun နုပျိုစဉ်ကာလက ရိုက်ကူးခဲ့တဲ့ကားလေးပါ။အကောင်းဆုံးတရုတ်LGBTကားတွေထဲမှာပါဝင်ပြီး ဆုတွေအများကြီးရရှိထားတဲ့ R-rated ဒရမ်မာ‌ကားကောင်းတစ်ကားပါ။၁၉၈၈မှာ ကလောင်အမည်ပဲပါပြီး ဘယ်သူဘယ်ဝါရေးမှန်းမသိတဲ့ ပုံနှိပ်တိုက်တွေကမထုတ်ဝေရဲတဲ့ အွန်လိုင်းပေါ်က ဝတ္ထုတစ်ပုဒ်ကိုအခြေခံပြီး ရိုက်ကူးထားတာပါ။၁၉၈၀နောက်ပိုင်းခေတ်တွေကို ဇာတ်အိမ်တည်ထားပါတယ်။ ဘဝမှာဝန်မခံချင်ရင်တောင်မှ နှစ်တွေဘယ်လောက်ပဲကြာပါစေ၊ ဘာတွေပဲပြောင်းလဲသွားပါစေ တချိန်ကလူတစ်ယောက်နဲ့ပတ်သတ်ဖူးတဲ့ကိစ္စတွေက လက်ဆတ်နေဆဲ၊ အတွေးထဲဝင်ရောက်နေဆဲဖြစ်တတ်ကြပါတယ်။ဒီလိုပဲ လိင်တူစွဲလမ်းမှုရှိပြီး ကြွယ်ဝတဲ့ စီးပွားရေးလုပ်ငန်းရှင် တစ်ယောက်ဆီကိုလည်း လန်ယုဆိုတဲ့ ပိုက်ဆံပြတ်နေတဲ့ မထုံတတ်တေးကောလိပ်ကျောင်းသားတစ်ယောက်က အခကြေးငွေယူပြီး လိင်ဖျော်ဖြေပေးဖြစ်တဲ့အခါမှာတော့ မငြင်းဆန်နိုင်တဲ့ အချစ်နှောင်ကြိုးတွေက တသက်တာလုံး တသသ လွမ်းမဝ ဖြစ်လာအောင် ရစ်ပတ်လာခဲ့ပါတယ်။လိင်တူချစ်ကြိုက်တာတွေကိုပွင့်လင်းစွာချပြခွင့်မသာတဲ့ခေတ်ကာလက ရှူးဂါးဒယ်ဒီနဲ့ သိမ်မွေ့တဲ့ကောင်လေးလန်ယုတို့ရဲ့ချစ်ခြင်းတစ်ခုကို ဒရမ်မာဆန်ဆန်ကြည့်ရှုခံစားရမှာပါ။(ဇာတ်လမ်းအညွှန်းနဲ့ ဘာသာပြန်ကတော့333ပါ။)File Size          :1.7GB,617MB &284MBQuality            :1080p Blur-ay,720p Blu-ray&480pFormat            :mp4Duration         :1hr & 26minsGenre              :Drama,RomanceTranslated by333Encoded byKinnov",
    "screenshot_links": [
      "https://image.tmdb.org/t/p/w300/1vPlBoNzScBC6bOwuPL0VtLDEh5.jpg",
      "https://image.tmdb.org/t/p/w300/1y7dUC38eF9jKLsD0jx3lJuDRMQ.jpg",
      "https://image.tmdb.org/t/p/w300/mj7h2XnWJgvSuO08TwKLpCqfN7c.jpg",
      "https://image.tmdb.org/t/p/w300/gQJt6yDdGstfSaIcgeW3V1ClU8f.jpg",
      "https://image.tmdb.org/t/p/w300/aoI4steHtaFfiGf6y03SyehqPdO.jpg",
      "https://image.tmdb.org/t/p/w300/ao6tECHbyXmqcdW1pMaK6VC8ZBR.jpg",
      "https://image.tmdb.org/t/p/w300/tWb3HPdM8wnep7Cgif"
    ],
    "thumbnail_link": "https://image.tmdb.org/t/p/w185/w8wHaRFlooOSkzMPw3IiMkRBLeG.jpg",
    "movie_links": [
      {
        "link": "https://www.cmvipmembers.com/check-movies/lan-yu-2001",
        "server": "VIP Links",
        "size": "1.7GB",
        "quality": "1080p Blu-ray"
      },
      {
        "link": "https://yoteshinportal.cc/cm-lan-yu-2001-1080-p-blu-ray-mp-4",
        "server": "yoteshinportal.cc",
        "size": "1.7GB",
        "quality": "1080p Blu-ray"
      },
      {
        "link": "https://usersdrive.com/51srq2jmxpfe.html",
        "server": "usersdrive.com",
        "size": "1.7GB",
        "quality": "1080p Blu-ray"
      },
      {
        "link": "https://megaup.net/3647u/[CM]Lan.Yu.2001.1080p.Blu-ray.mp4",
        "server": "megaup.net",
        "size": "1.7GB",
        "quality": "1080p Blu-ray"
      },
      {
        "link": "https://mega.nz/file/BnBQwJDQ#h-fYqQC89dnDDFaUYCVwnzj2xlBy_iiN2hSQ7PnK810",
        "server": "mega.nz",
        "size": "1.7GB",
        "quality": "1080p Blu-ray"
      },
      {
        "link": "https://yoteshinportal.cc/cm-lan-yu-2001-720-p-blu-ray-mp-4",
        "server": "yoteshinportal.cc",
        "size": "617MB",
        "quality": "720p Blu-ray"
      },
      {
        "link": "https://usersdrive.com/9bs5ea8s1a66.html",
        "server": "usersdrive.com",
        "size": "617MB",
        "quality": "720p Blu-ray"
      },
      {
        "link": "https://megaup.net/3647h/[CM]Lan.Yu.2001.720p.Blu-ray.mp4",
        "server": "megaup.net",
        "size": "617MB",
        "quality": "720p Blu-ray"
      },
      {
        "link": "https://mega.nz/file/InYjCIpC#Dz8oKJQW3ozq-70VkTWrj8v1lerOBOQ_mJtCO4r2dSM",
        "server": "mega.nz",
        "size": "617MB",
        "quality": "720p Blu-ray"
      },
      {
        "link": "https://sbfast.com/4ss94u8bh4vx.html",
        "server": "streamsb.com",
        "size": "617MB",
        "quality": "720p Blu-ray"
      },
      {
        "link": "https://yoteshinportal.cc/cm-lan-yu-2001-480-p-mp-4",
        "server": "yoteshinportal.cc",
        "size": "284MB",
        "quality": "480p"
      },
      {
        "link": "https://usersdrive.com/h4cz7s8tw2wm.html",
        "server": "usersdrive.com",
        "size": "284MB",
        "quality": "480p"
      },
      {
        "link": "https://megaup.net/1K9cz/[CM]Lan.Yu.2001.480p.mp4",
        "server": "megaup.net",
        "size": "284MB",
        "quality": "480p"
      },
      {
        "link": "https://mega.nz/file/ZzhDXKrI#K4XfRy3jOyo9k0Jtw30xqS0HPp6WbGG9nrspWwYKFPo",
        "server": "mega.nz",
        "size": "284MB",
        "quality": "480p"
      },
      {
        "link": "https://sbfast.com/w63yy5bmht8b.html",
        "server": "streamsb.com",
        "size": "284MB",
        "quality": "480p"
      }
    ],
    "trailer": {
      "video_id": "MYqJ1Pv9o4s",
      "video_url": "https://www.youtube.com/watch?v=MYqJ1Pv9o4s",
      "embed_url": "https://www.youtube.com/embed/MYqJ1Pv9o4s"
    }
  },
  {
    "metadata": "R|2001|122 min|Horror,Mystery,Thriller",
    "rating": {
      "rating": "6.8/10",
      "rating_count": "136,803"
    },
    "title": "From Hell (2001)",
    "description": "CM Fan ေတြ အတြက္ မင္းသားႀကီး Johnny Depp ငယ္စဥ္က သရုပ္ေဆာင္ခဲ့တဲ့ရုပ္ရွင္ကားေကာင္း တစ္ခုနဲ႔ မိတ္ဆက္ေပးခ်င္ပါတယ္၂၀၀၁ ခုႏွစ္က ထြက္ရွိခဲ့တဲ့ From Hell ဆိုတဲ့သည္းထိတ္ရင္ဖုိ စံုေထာက္ ရုပ္ရွင္ကားျဖစ္ပါတယ္IMDb Rating 6.8 ထိ ရရွိထားပါတယ္Johnny Depp နဲ႔ အတူ မင္းသမီး Heather Graham ပါ သရုပ္ေဆာင္ထားပါတယ္ဇတ္လမ္းပံုစံကေတာ့ ဒုစရိုက္မႈေတြ ႀကီးစိုးတဲ့ ၿမိဳ႕တစ္ခုမွာရဲစံုေထာက္ နာမည္ေက်ာ္ အက္ဗာလုိင္း ဆိုတဲ့ လူတစ္ေယာက္ရွိတယ္သူက ဘယ္ေလာက္ထိ နာမည္ႀကီးလဲဆိုရင္ ေသေနတဲ့သူရဲ႕အေလာင္းကို ကိုင္ၾကည့္ရံုနဲ႔ လူသတ္မႈကို ေျခရာခံႏုိင္ပါသတဲ့စိတ္စြမ္းအင္လဲ ရွိၿပီး လူသတ္မႈေတြ မျဖစ္ခင္ ႀကိဳတင္အာရံုရတက္ပါတယ္သူက လူထူးလူဆန္းလို ျဖစ္ေနၿပီး ၿမိဳ႕နယ္ ရဲတပ္ဖြဲ႔ရဲ႕ အားကိုးရာလဲျဖစ္ပါတယ္ပံုစံ အရ ေျပာရရင္ မင္းသိခၤ ၀တၱဳထဲက ဆားပုလင္း ႏွင္းေမာင္ လိုေပါ့…တစ္ရက္မွာေတာ့ အဲ့ဒီ ၿမိဳ႕ေသးေသးေလးမွာ အမႈအခင္း ထူးထူးဆန္းဆန္းတစ္ခုျဖစ္ခဲ့ပါတယ္…အဲ့ဒါကေတာ့ ျပည့္တန္ဆာ ေတြကို လုိက္သတ္ေနတဲ့ ကြင္းဆက္လူသတ္သမားတစ္ေယာက္ ရွိေနၿပီး ျပည့္တန္ဆာေတြကို သတ္ၿပီးရင္ လိင္အဂၤါကို လွီးယူသြားတက္ပါတယ္ရဲေတြလဲ အေတာ္ ေခါင္းစားေနပါၿပီ ဒီအမႈ ကို ေျဖရွင္းႏုိင္မယ့္သူကလဲ တစ္ေယာက္ပဲ ရွိပါတယ္သူကေတာ့ အက္ဗာလုိင္း ေပါ့….ဇတ္လမ္းက စၾကည့္ကတည္းကေန အဆံုးထိ အင္မတန္ စိတ္၀င္စားဖို႔ေကာင္းပါတယ္အဂၤလန္ဘုရင္မႀကီး နဲ႔ ေတာ္၀င္မ်ိဳးဆက္ေတြ အပါအ၀င္ ျမန္မာျပည္မွာနာမည္ႀကီးတဲ့ပလွ်ဴးေခါင္းျဖတ္ ဂိုဏ္းလို႔ နာမည္ႀကီးတဲ့ ဖရီးေမဆင္ လို ဂိုဏ္းေတြပါ ပါ၀င္လာခဲ့ပါတယ္Firday ည အတြက္ ညစာ လို႔ သက္မွတ္ၿပီး ၾကည့္ရႈႏိုင္ပါၿပီ…ဇတ္လမ္းကို ေမသူ က ဘာသာျပန္ေပးထားပါတယ္",
    "screenshot_links": [
      "https://image.tmdb.org/t/p/w300/7MtD34lQ0dWmyNSbte4VZuQRt0i.jpg",
      "https://image.tmdb.org/t/p/w300/2aLBewiag47U7Ef8rMZSlYQhi0P.jpg",
      "https://image.tmdb.org/t/p/w300/oYK1KfAABFQEnbgpZHpHu2ZuUMj.jpg",
      "https://image.tmdb.org/t/p/w300/5Fxggfe5ALdfxxbXtZZsKdV0hg5.jpg",
      "https://image.tmdb.org/t/p/w300/tljDWCWEJtyosIXh0VGbtOJcvUA.jpg",
      "https://image.tmdb.org/t/p/w300/9v50U5lj3GTGaUaxpxZ4rmHFDpr.jpg",
      "https://image.tmdb.org/t/p/w300/yzjFM2hjxA4Wu7oIjiJ1et1yOJe.jpg",
      "https://image.tmdb.org/t/p/w300/pRH9jtLGsanbavhPKlfUmXB6aEf.jpg"
    ],
    "thumbnail_link": "https://channelmyanmar.org/wp-content/uploads/2018/11/MV5BMTM1MjkxNTQxMV5BMl5BanBnXkFtZTYwMDMxNDg2._V1_.jpg",
    "movie_links": [
      {
        "link": "https://yoteshinportal.cc/from-hell-2001-mm-sub-mp-4-1",
        "server": "yoteshinportal.cc",
        "size": "1.45 GB",
        "quality": ""
      },
      {
        "link": "https://megaup.net/2eXQ3/From_Hell_[2001]_(MM_Sub).mp4",
        "server": "megaup.net",
        "size": "1.45 GB",
        "quality": ""
      },
      {
        "link": "https://upstream.to/iwfndv5668ay",
        "server": "upstream.to",
        "size": "1.45 GB",
        "quality": ""
      },
      {
        "link": "https://usersdrive.com/jm0ja7ij7dx8.html",
        "server": "usersdrive.com",
        "size": "1.45 GB",
        "quality": ""
      },
      {
        "link": "https://www.cmvipmembers.com/check-movies/from-hell-2001-mm-sub",
        "server": "VIP Links",
        "size": "1.45 GB",
        "quality": ""
      }
    ],
    "trailer": {
      "video_id": "yw8US3gS37w",
      "video_url": "https://www.youtube.com/watch?v=yw8US3gS37w",
      "embed_url": "https://www.youtube.com/embed/yw8US3gS37w"
    }
  },
  {
    "metadata": "PG-13|2001|106 min|Action,Crime,Thriller",
    "rating": {
      "rating": "6.7/10",
      "rating_count": "298,113"
    },
    "title": "The Fast and the Furious (2001) Fast and Furious 1",
    "description": "ဒွမ်တို့အဖွဲ့ဟာ မြို့ရဲ့ အကြီးမားဆုံးသောခိုးမှုတွေမှာ ရဲတပ်ဖွဲ့တွေရဲ့ သံသယအရှိဆုံးသူတွေပါ…အချီကြီးမှချတတ်သလို ပိရိလွန်းပြီးလက်တွဲညီလွန်းတဲ့သူတို့အဖွဲ့ကြောင့် ရဲတပ်ဖွဲ့ဟာကြိတ်မနိုင်ခဲမရ ဘယ်ကအစကောက်ပြီးလိုက်ရမှန်းမသိဖြစ်နေတယ်…အဲ့ဒီအချိန်မှာပဲ ကားမောင်းကျွမ်းကျင်ပြီး ဂျလေဘီပုံပေါက်နေတဲ့ ဘရိုင်ယန်ကိုသူလျှိုအဖြစ်စေခိုင်းရင်း ဒွန်တို့အဖွဲ့ကို ရဲတပ်ဖွဲ့ဟာ ဖြိုခွင်းဖို့ကြိုးစားပါတော့တယ်….File Size : (2.06GB) ,(0.99 GB)Quality : Blu-Ray 10805.1CH , 720pRunning Time : 1hr 46minFormat : Mp4Genre :Action, Crime, ThrillerSubtitle : Myanmar Subtitle (Hard Sub)Source : 1080p BluRay x264-SPARKSTranslated by Thura Zarni AungEncoded by Phyo Pyae/Thanhtike Zaw",
    "screenshot_links": [
      "https://image.tmdb.org/t/p/w300/lmIqH8Qsv3IvDg0PTFUuVr89eBT.jpg",
      "https://image.tmdb.org/t/p/w300/eRh8pHaklhBahLtfkiVPAMpZbf3.jpg",
      "https://image.tmdb.org/t/p/w300/mPd8pLSCXGuqlZLXQS9QXb6pkXW.jpg",
      "https://image.tmdb.org/t/p/w300/iBAWBV3j6lzUuB1ncKYaVBrJnKt.jpg",
      "https://image.tmdb.org/t/p/w300/rcN2N8pTGpLDnL65J98ckvi2rTE.jpg",
      "https://image.tmdb.org/t/p/w300/whXKb7gQGe0MyOJxzymveK9peTK.jpg",
      "https://image.tmdb.org/t/p/w300/1UCzsTUPru0k4LETgPUGtBdGMor.jpg",
      "https://image.tmdb.org/t/p/w300/dUx87YOHJAbWJIpG9O5iSlSu2x.jpg",
      "https://image.tmdb.org/t/p/w300/aghYHbG83mwgNfIFiSSmkiX05gh.jpg",
      "https://image.tmdb.org/t/p/w300/vYCBqoL0xWx3G5ElTowzrGf9Oe1.jpg",
      "https://image.tmdb.org/t/p/w300/an6pyUEoFP8T25nH9CwQ5iUu3Jr.jpg",
      "https://image.tmdb.org/t/p/w300/1YWUmuwyOhMDsxtSNK4Kd6hz3DL.jpg",
      "https://image.tmdb.org/t/p/w300/nwLVjjpWoBbpbde7Jd4ljYzD8gn.jpg",
      "https://image.tmdb.org/t/p/w300/bSh3AAZ6OQk0rKgJjOdw6UXl26q.jpg",
      "https://image.tmdb.org/t/p/w300/gH8pdqF9H3xzYjtSrz4xZt1rLpJ.jpg",
      "https://image.tmdb.org/t/p/w300/pMRsB4yFH38lANm8HgoCzBonYmK.jpg",
      "https://image.tmdb.org/t/p/w300/lwD3heykXZ5KCoshV8othLt3q5I.jpg"
    ],
    "thumbnail_link": "https://channelmyanmar.org/wp-content/uploads/2017/12/MV5BNzlkNzVjMDMtOTdhZC00MGE1LTkxODctMzFmMjkwZmMxZjFhXkEyXkFqcGdeQXVyNjU0OTQ0OTY@._V1_SY1000_CR006721000_AL_.jpg",
    "movie_links": [
      {
        "link": "https://yoteshinportal.cc/the-fast-and-the-furious-2001-blu-ray-1080-p-5-1-ch-mp-4-1",
        "server": "yoteshinportal.cc",
        "size": "2.06GB",
        "quality": "BLU-RAY1080P5.1CH"
      },
      {
        "link": "https://megaup.net/1Ukx8/The_Fast_and_the_Furious.2001.BLU-RAY1080P5.1CH.mp4",
        "server": "megaup.net",
        "size": "2.06GB",
        "quality": "BLU-RAY1080P5.1CH"
      },
      {
        "link": "https://usersdrive.com/mtuu6wrn2bvo.html",
        "server": "usersdrive.com",
        "size": "2.06GB",
        "quality": "BLU-RAY1080P5.1CH"
      },
      {
        "link": "https://mega.nz/file/dTNy3SAT#310iP9tAhkzO7L7lrjNrQ24d7ds7YpkvlG9ymTFMvzQ",
        "server": "mega.nz",
        "size": "2.06GB",
        "quality": "BLU-RAY1080P5.1CH"
      },
      {
        "link": "https://yoteshinportal.cc/fast-and-furious-1-the-fast-and-the-furious-2001-mm-sub-mp-4-2",
        "server": "yoteshinportal.cc",
        "size": "0.99 GB",
        "quality": "720p"
      },
      {
        "link": "https://usersdrive.com/d4qarmbgc1a9.html",
        "server": "usersdrive.com",
        "size": "0.99 GB",
        "quality": "720p"
      },
      {
        "link": "https://megaup.net/3ytT6/Fast_And_Furious_1_-_The_Fast_And_The_Furious_[2001]_(MM_Sub).mp4",
        "server": "megaup.net",
        "size": "0.99 GB",
        "quality": "720p"
      },
      {
        "link": "https://mega.nz/file/hS0BHIDI#hej47S-QKZKTSqIoIh4JmY_oHVWJJWeLg8cjSq0F5Vw",
        "server": "mega.nz",
        "size": "0.99 GB",
        "quality": "720p"
      },
      {
        "link": "https://sbrapid.com/7u63io7w9kz8.html",
        "server": "streamsb.com",
        "size": "0.99 GB",
        "quality": "720p"
      }
    ],
    "trailer": {
      "video_id": "ar00z32bXNQ",
      "video_url": "https://www.youtube.com/watch?v=ar00z32bXNQ",
      "embed_url": "https://www.youtube.com/embed/ar00z32bXNQ"
    }
  },
  {
    "metadata": "R|2001|1h 39m|Action,Crime,Thriller",
    "rating": {
      "rating": "6.5/10",
      "rating_count": "194000"
    },
    "title": "Swordfish (2001)",
    "description": "Swordfish (2001)” Nudity Scene အနည်းငယ်နှင့် ကြမ်းတမ်းသော အပြောအဆိုများ ပါ၀င်သောကြောင့် သတိထားကြည့်ရှုပါရန် “ဒီကားလေးကတော့ 2001 ခုနှစ်ကထွက်ထားတဲ့ သည်းထိတ်ရင်ဖိုအက်ရှင် ကားကောင်းလေးပါ။ ဆုငါးဆုနဲ့ စံကာတင်ဆု (၁၀)ဆု၀င်ထားပြီး IMDb rating – 6.5/10 ရထားပါတယ်။ နာမည်ကြီးသရုပ်ဆောင်တွေဖြစ်တဲ့ Wolverine မင်းသားကြီး Hugh Jackman ရယ်၊ X-Men ထဲမှာပဲ Storm အဖြစ်သရုပ်ဆောင်ခဲ့တဲ့ အော်စကာဆုရှင် Halle Berry ရယ်၊ 1970-80 ပြည့်နှစ်တွေက ဗီလိန်မင်းသားလို့မျက်မှန်းတန်းမိကြတဲ့ John Travolta ရယ်၊ Avengers ထဲက War Machine သရုပ်ဆောင် Don Cheadle နဲ့ဆိုတော့ Cast တွေနဲ့တင် စိတ်မပျက်စေရမယ့်ဇာတ်ကားမျိုးပါပဲ။စတန်က ခံ၀န်နဲ့လွတ်နေတဲ့ ဟက်ကာတစ်ယောက်ပါ။ တစ်နေ့ သူ့ဆီကို ဂျင်းဂျားဆိုတဲ့အလှပဂေးလေးက လူတစ်ယောက်နဲ့လိုက်တွေ့ဖို့ လာခေါ်ပါတယ်။ တွေ့ခွင့်မရတဲ့ သမီးဖြစ်သူကိုပြန်ရစေမယ်လို့ မက်လုံးပေးတဲ့အတွက် စတန်လိုက်သွားရာကနေ ဂေဘရီရယ်ဆိုတဲ့သူနဲ့တွေ့ပြီး အရှုပ်တော်ပုံထဲရောက်သွားတဲ့အကြောင်းကို စိတ်၀င်တစားကြည့်ရှုရမှာပါ။(ဒီဇာတ်ကားနဲ့အညွှန်းကိုSoe Thiri Sweမှ ပြန်ဆို ရေးသားထားပါတယ်)Size – 1.95GB, 875MBQuality – 1080p, 720pIMDb Rating – 6.5/10Format – mp4Duration – 1H 39MinGenre – Action, Crime, ThrillerSubtitle – Myanmar Subtitle (Hardsub)Translated bySoe Thiri SweEncoded by Y",
    "screenshot_links": [
      "https://image.tmdb.org/t/p/w300/eSxvC0Qw0A9AfI355MF9dSItrfR.jpg",
      "https://image.tmdb.org/t/p/w300/78KbfgOV6M5bX9ngL3dFAtBHEIA.jpg",
      "https://image.tmdb.org/t/p/w300/uS1Y1zEate5haqPZNfUETXyHT5Q.jpg",
      "https://image.tmdb.org/t/p/w300/qL2HrmCEAyQEyeLiJN4hhnbu0M1.jpg",
      "https://image.tmdb.org/t/p/w300/lTIA9OTn5S5GUSe9WG17QaXN1vc.jpg",
      "https://image.tmdb.org/t/p/w300/eU3HxRTWqoSG4idsYj8zD9UGan.jpg",
      "https://image.tmdb.org/t/p/w300/xqLcFBmR0GLHFxwkShgT3Tiv6T8.jpg",
      "https://image.tmdb.org/t/p/w300/9mjJswW4RzN7qBsJvnTMS3URFv3.jpg",
      "https://image.tmdb.org/t/p/w300/TYNAeYFbPD4MhsEe0CmVJfS8fY.jpg",
      "https://image.tmdb.org/t/p/w300/3wmn39gg6EexG5HudvYjFqm57Rn.jpg",
      "https://image.tmdb.org/t/p/w300/pnSmWDOJ35zHzWR0n5gxoxKGgOP.jpg",
      "https://image.tmdb.org/t/p/w300/zCRaJZJYMt51vCjCfPLAbtZYyz5.jpg"
    ],
    "thumbnail_link": "https://image.tmdb.org/t/p/w185/mM6h4jMqC4q5IaFgBIGKQDLnRU.jpg",
    "movie_links": [
      {
        "link": "https://yoteshinportal.cc/cm-swordfish-2001-1080-p-mp-4",
        "server": "yoteshinportal.cc",
        "size": "1.95GB",
        "quality": "1080p"
      },
      {
        "link": "https://megaup.net/1iXce/(CM)_Swordfish_(2001)_1080p.mp4",
        "server": "megaup.net",
        "size": "1.95GB",
        "quality": "1080p"
      },
      {
        "link": "https://mega.nz/file/iNtxxZaY#n17tk1bVRgRSm5o296NvToC5I-vjgmM2-8nQqJveX4w",
        "server": "mega.nz",
        "size": "1.95GB",
        "quality": "1080p"
      },
      {
        "link": "https://usersdrive.com/t92lcldkixt1.html",
        "server": "usersdrive.com",
        "size": "1.95GB",
        "quality": "1080p"
      },
      {
        "link": "https://yoteshinportal.cc/cm-swordfish-2001-720-p-mp-4",
        "server": "yoteshinportal.cc",
        "size": "875MB",
        "quality": "720p"
      },
      {
        "link": "https://megaup.net/1iXc5/(CM)_Swordfish_(2001)_720p.mp4",
        "server": "megaup.net",
        "size": "875MB",
        "quality": "720p"
      },
      {
        "link": "https://mega.nz/file/XZUjRaiQ#qzSonQDX5avf1ds7VQDmV67Ctt6WGag7u7D8bKzbfFQ",
        "server": "mega.nz",
        "size": "875MB",
        "quality": "720p"
      },
      {
        "link": "https://usersdrive.com/kjwo1owxk8ec.html",
        "server": "usersdrive.com",
        "size": "875MB",
        "quality": "720p"
      },
      {
        "link": "https://sfastwish.com/pjbvulkfdzyz",
        "server": "streamsb.com",
        "size": "875MB",
        "quality": "720p"
      },
      {
        "link": "https://streamvid.net/nyb2exmaf3hy",
        "server": "streamvid.io",
        "size": "875MB",
        "quality": "720p"
      }
    ],
    "trailer": {
      "video_id": "lFwtY1bxlNc",
      "video_url": "https://www.youtube.com/watch?v=lFwtY1bxlNc",
      "embed_url": "https://www.youtube.com/embed/lFwtY1bxlNc"
    }
  },
  {
    "metadata": "Unrated|2001|1h 30m|Comedy,Horror,Thriller",
    "rating": {
      "rating": "/10",
      "rating_count": "174"
    },
    "title": "Body Jumper (2001)",
    "description": "Body Jumper (2001)” အကြည်ရဖို့မလွယ်လို့ 480p ကိုပဲ ကြည့်ရပြေအောင် ချဲ့ကုတ်ပေးထားပါတယ်ခင်ဗျာ “တစ်ချိန်က နာမည်ဆိုးနဲ့ကျော်ကြားတဲ့ သရဲမ ဘော့ဘ်ဟာ သူကျင်လည်ကျက်စားရာရွာလေးမှာ ယောက်ျားတွေကို မြူစွယ်ရင်း အသည်းဖောက်စားလေ့ရှိတယ်။ အဲဒီတော့ ရွာသားတွေလည်း တစ််နေ့တခြားဆိုးသွမ်းလာတဲ့ ဘော့ဘ်ကို သရဲနှင်ဆရာတွေခေါ်ပြီး ရေတွင်းပျက်တစ်ခုထဲ ပိတ်လှောင်ခဲ့ကြတယ်။နှစ်ပေါင်း ၇၀အကြာမှာတော့ မြို့ကကျောင်းသားတစ်အုပ် အဲဒီဆမ်ခေါ်ရွာလေး တိုးတက်ဖို့ဆိုပြီး ကျောင်းပရောဂျက်အတွက် ရောက်လာကြတယ။ သူတို့ထဲက သိပ်လှတဲ့ ကောင်မလေး ဂဲ ရေချိုးတာကို ချောင်းကြရင်း သရဲမဘော့ဘ်ကို မတော်တဆ လွတ်မြောက်သွားစေခဲ့တယ်။ ဘော့ဘ်ဟာ ဂဲဆီ ဝင်ပူးပြီး ကျောင်းသားအုပ်စုနဲ့အတူ ဘန်ကောက်မြို့ကို ပြန်လိုက်သွားချိန်မှာတော့…ပေါ့ပေါ့ပါးပါး ကြည့်ရှုရမယ့် ထိုင်းသရဲဟာသကားလေးဖြစ်တာမို့ အားပေးလိုက်ကြပါဦး…(ဒီဇာတ်ကားနဲ့အညွှန်းကိုMugiwara Yaမှ ပြန်ဆို ရေးသားထားပါတယ်)Size – 1.4GB, 760MBQuality – 1080p, 720pFormat – mp4Duration – 1H 30MinGenre – Comedy, Horror, ThrillerSubtitle – Myanmar Subtitle (Hardsub)Translated byMugiwara YaEncoded by Y",
    "screenshot_links": [
      "https://image.tmdb.org/t/p/w300/AmgPcln5ldPXFjESaRoy7ArSYRN.jpg"
    ],
    "thumbnail_link": "https://image.tmdb.org/t/p/w185/aZ2CWumYRunOWquAEtG293xrZWK.jpg",
    "movie_links": [
      {
        "link": "https://yoteshinportal.cc/cm-body-jumper-2001-720-p-mp-4",
        "server": "yoteshinportal.cc",
        "size": "1.4GB",
        "quality": "720p"
      },
      {
        "link": "https://megaup.net/2xw9i/(CM)_Body_Jumper_(2001)_720p.mp4",
        "server": "megaup.net",
        "size": "1.4GB",
        "quality": "720p"
      },
      {
        "link": "https://mega.nz/file/eIwUwZ6J#2iiW69jF0Ngme5k2KNeVka80e65t5ZAXbFPERdRl0nA",
        "server": "mega.nz",
        "size": "1.4GB",
        "quality": "720p"
      },
      {
        "link": "https://usersdrive.com/u7dbd68bcsz0.html",
        "server": "usersdrive.com",
        "size": "1.4GB",
        "quality": "720p"
      },
      {
        "link": "https://sbchill.com/wax9zmipnwt9.html",
        "server": "streamsb.com",
        "size": "1.4GB",
        "quality": "720p"
      },
      {
        "link": "https://streamvid.net/7n858xle1zac",
        "server": "streamvid.io",
        "size": "1.4GB",
        "quality": "720p"
      },
      {
        "link": "https://yoteshinportal.cc/cm-body-jumper-2001-480-p-mp-4",
        "server": "yoteshinportal.cc",
        "size": "760MB",
        "quality": "480p"
      },
      {
        "link": "https://megaup.net/1bBe9/(CM)_Body_Jumper_(2001)_480p.mp4",
        "server": "megaup.net",
        "size": "760MB",
        "quality": "480p"
      },
      {
        "link": "https://mega.nz/file/PVhCBRQa#XtKO49bo1fnO6_nSQQ9gBg_uRyJg1b2P3wU9mO6JQZo",
        "server": "mega.nz",
        "size": "760MB",
        "quality": "480p"
      },
      {
        "link": "https://usersdrive.com/xqk7f6lulre2.html",
        "server": "usersdrive.com",
        "size": "760MB",
        "quality": "480p"
      },
      {
        "link": "https://sbchill.com/6w9mthor8enl.html",
        "server": "streamsb.com",
        "size": "760MB",
        "quality": "480p"
      },
      {
        "link": "https://streamvid.net/m4jy4eoo9hgp",
        "server": "streamvid.io",
        "size": "760MB",
        "quality": "480p"
      }
    ],
    "trailer": {
      "video_id": "IayW68DQlB8",
      "video_url": "https://www.youtube.com/watch?v=IayW68DQlB8",
      "embed_url": "https://www.youtube.com/embed/IayW68DQlB8"
    }
  },
  {
    "metadata": "R|2001|119 min|Adult,Drama,Romance",
    "rating": {
      "rating": "6.2/10",
      "rating_count": "10,220"
    },
    "title": "(21+)Intimacy[2001]",
    "description": "(21+)Intimacy[2001]Dark Side Production မှ တင်ဆက်သည်။IMDb..6.2(လူကြီးမင်းတို့ရဲ့ သမာဓိအားကို စမ်းသပ်စစ်ဆေးပေးသည့်အပြင်အိမ်ထောင်ရေးပညာပေး ဆုတွေတသီကြီးရထားတဲ့အဆင့်အတန်းမြှင့်ကားမို့ BLU-RAY 1080P,720Pတို့ဖြင့်ပြန်လည်တင်ဆက်ပေးထားသည်…)ဗုဒ္ဓဟူးနေ့…အပတ်တိုင်းရဲ့ ဒီနေ့မှာဂီတပညာရှင်ဟောင်း Bar Leaderဆီအမျိုးသမီးတစ်ယောက်ရောက်လာပြီးအပြန်အလှန် ကာမဆန္ဒဖြေဖျောက်ကြတယ်….တစ်ယောက်နဲ့တစ်ယောက်ငြိတွယ်ပုံတွေက ဆန်းကျယ်တယ်.. စကားတွေအများကြီးမဆိုကြဘူး..ချစ်ရည်လဲ့နေတဲ့ မျက်လုံးတွေနဲ့ပဲခပ်ကြမ်းကြမ်းကဗျာတွေဖွဲ့သီကြတယ်…ဒီကားက အိမ်ထောင်ရေးဇတ်လမ်းကောင်းလေးဖြစ်သလို imdb..6.2လည်းရထားပါတယ်…သို့ပေမယ့်[21+] ခန်းတွေပါဝင်တာမို့ဒီကားရဲ့ကောင်းမွန်တဲ့ message လေးတွေရယူချင်တဲ့သူတွေအဖို့  ဘယ်လိုကြည့်သင့်တယ်ဆိုတာ အထွေအထူးသတိမပေးတော့ပါဘူးနော်…နောက်ပြီးဒီကားက ဆု (၆)ဆုရထားလေတော့ ခင်ဗျားတို့ကြည့်တာ တကယ့် တန်းဝင်ကားတစ်ကားကိုကြည့်နေတယ်ဆိုတာလည်း သတိရပြီး ဂုဏ်ယူသင့်တဲ့အကြောင်းလေး ထပ်လောင်းပြောကြားပါရစေ…File Size :(2GB) And (850 MB)Quality : BLU-RAY 1080P,720PRunning Time : 1hr 59minFormat : Mp4Genre :Drama,Romance,Subtitle : Myanmar Subtitle (Hard Sub)Translated by WiRa AungEncoded by Darkside BGR",
    "screenshot_links": [
      "https://image.tmdb.org/t/p/w300/z1QcTGsj7A4vFtHmDDzqXdCtUM6.jpg",
      "https://image.tmdb.org/t/p/w300/gYYjUiKvEigysglsQJnDnkFce27.jpg",
      "https://image.tmdb.org/t/p/w300/jfof9TPHkXDzRNvKkqqcFkHd1OS.jpg"
    ],
    "thumbnail_link": "https://image.tmdb.org/t/p/w185/tpdXXWanM7IUA9E4ZkRXa6JqLCv.jpg",
    "movie_links": [
      {
        "link": "https://usersdrive.com/5a7qbqe8ug8k.html",
        "server": "usersdrive.com",
        "size": "2GB",
        "quality": "BLU-RAY 1080P"
      },
      {
        "link": "https://usersdrive.com/cb46kf980t60.html",
        "server": "usersdrive.com",
        "size": "850MB",
        "quality": "BLU-RAY 720P"
      },
      {
        "link": "https://megaup.net/4ePL4/Intimacy.2001.BLU-RAY.1080P.mp4",
        "server": "megaup.net",
        "size": "2GB",
        "quality": "BLU-RAY 1080P"
      },
      {
        "link": "https://megaup.net/4UNdi/Intimacy.2001.BLU-RAY.720P.mp4",
        "server": "megaup.net",
        "size": "850MB",
        "quality": "BLU-RAY 720P"
      },
      {
        "link": "https://1fichier.com/?j3ulaet8jqi55egv9o6m",
        "server": "mega.nz",
        "size": "2GB",
        "quality": "BLU-RAY 1080P"
      },
      {
        "link": "https://1fichier.com/?bqgh4uekljz7d1xdbt95",
        "server": "mega.nz",
        "size": "850MB",
        "quality": "BLU-RAY 720P"
      },
      {
        "link": "https://upstream.to/1jcp8bkttlhf",
        "server": "upstream.to",
        "size": "2GB",
        "quality": "BLU-RAY 1080P"
      },
      {
        "link": "https://upstream.to/95xnb3cmgwgc",
        "server": "upstream.to",
        "size": "850MB",
        "quality": "BLU-RAY 720P"
      },
      {
        "link": "https://1fichier.com/?j3ulaet8jqi55egv9o6m",
        "server": "1fichier.com",
        "size": "2GB",
        "quality": "BLU-RAY 1080P"
      },
      {
        "link": "https://1fichier.com/?bqgh4uekljz7d1xdbt95",
        "server": "1fichier.com",
        "size": "850MB",
        "quality": "BLU-RAY 720P"
      },
      {
        "link": "https://yoteshinportal.cc/intimacy-2001-blu-ray-1080-p-mp-4",
        "server": "yoteshinportal.cc",
        "size": "2GB",
        "quality": "BLU-RAY 1080P"
      },
      {
        "link": "https://yoteshinportal.cc/intimacy-2001-blu-ray-720-p-mp-4",
        "server": "yoteshinportal.cc",
        "size": "850MB",
        "quality": "BLU-RAY 720P"
      }
    ],
    "trailer": null
  },
  {
    "metadata": "|2001||Adventure,Comedy,Drama",
    "rating": {
      "rating": "5.7/10",
      "rating_count": "4,292"
    },
    "title": "Princess of Thieves (2001)",
    "description": "Princess of Thieves (2001)===================IMDb Rating – 5.7/10#Unicodeဒီတစ်ခေါက်တော့ ပုံပြင်တွေကို ကြိုက်နှစ်သက်တဲ့ ပရိတ်သတ်တွေအတွက် ဒါရိုက်တာ Peter Hewittရိုက်ကူးထားတဲ့ Princess of Thieves နဲ့ မိတ်ဆက်ပေးပါရစေ။ ဒီဇာတ်ကားက ရော်ဘင်ဟုထ် နဲ့ သူ့သမီးဇာတ်ကြောင်းလေးကို ရိုက်ထားတာပါ။ဒီဇာတ်ကားထဲမှာ ဘုရင်သေဆုံးသွားတော့ မြို့စားမင်းရဲ့ အာဏာတပ်မက်မှု့တွေကြောင့် နောက်နန်းတက်မဲ့ဘုရင့်သားတော် တစ်ပါးကို ကြေးစားငှါးရမ်းပြီး လိုက်လံ သတ်ဖြတ်ခိုင်းပါတော့တယ်။ တချိန်ထဲမှာပဲ ဘုရင့်အပေါ် သစ္စာစောင့်သိတဲ့ ပြည်သူတွေနှင့် ပြည်သူ့အချစ်တော် ရော်ဘင်ဟုထ်ရယ် သူ့သမီးလေးရယ်ကမင်းသားလေးကို မြို့စားမင်းရဲ့ လုပ်ကြံသတ်ဖြတ်မှု လက်ထဲကနေ ဘယ်လိုကယ်တင်ကြမလဲ…. နောက်ပြီးရော်ဘင်ဟုထ်ရဲ့ သမီးနဲ့ မင်းသားလေးရဲ့ အချစ်ဇာတ်လမ်းလေးတွေကို ဒီကားထဲမှာ ကြည့်ရှုရမှာပါ………(ဒီဇာတ်လမ်းရဲ့ အညွှန်းနဲ့ဘာသာပြန်ရေးသားပေးသူကတော့ Parris ပဲဖြစ်ပါတယ်။)#Zawgyiဒီတစ္ေခါက္ေတာ့ ပုံျပင္ေတြကို ႀကိဳက္ႏွစ္သက္တဲ့ ပရိတ္သတ္ေတြအတြက္ ဒါ႐ိုက္တာ Peter Hewitt႐ိုက္ကူးထားတဲ့ Princess of Thieves နဲ႔ မိတ္ဆက္ေပးပါရေစ။ ဒီဇာတ္ကားက ေရာ္ဘင္ဟုထ္ နဲ႔ သူ႔သမီးဇာတ္ေၾကာင္းေလးကို ႐ိုက္ထားတာပါ။ဒီဇာတ္ကားထဲမွာ ဘုရင္ေသဆုံးသြားေတာ့ ၿမိဳ႕စားမင္းရဲ႕ အာဏာတပ္မက္မႈ႕ေတြေၾကာင့္ ေနာက္နန္းတက္မဲ့ဘုရင့္သားေတာ္ တစ္ပါးကို ေၾကးစားငွါးရမ္းၿပီး လိုက္လံ သတ္ျဖတ္ခိုင္းပါေတာ့တယ္။ တခ်ိန္ထဲမွာပဲ ဘုရင့္အေပၚ သစၥာေစာင့္သိတဲ့ ျပည္သူေတြႏွင့္ ျပည္သူ႔အခ်စ္ေတာ္ ေရာ္ဘင္ဟုထ္ရယ္ သူ႔သမီးေလးရယ္ကမင္းသားေလးကို ၿမိဳ႕စားမင္းရဲ႕ လုပ္ႀကံသတ္ျဖတ္မႈ လက္ထဲကေန ဘယ္လိုကယ္တင္ၾကမလဲ…. ေနာက္ၿပီးေရာ္ဘင္ဟုထ္ရဲ႕ သမီးနဲ႔ မင္းသားေလးရဲ႕ အခ်စ္ဇာတ္လမ္းေလးေတြကို ဒီကားထဲမွာ ၾကည့္ရႈရမွာပါ………(ဒီဇာတ္လမ္းရဲ႕ အၫႊန္းနဲ႔ဘာသာျပန္ေရးသားေပးသူကေတာ့ Parris ပဲျဖစ္ပါတယ္။)Quality –  1080p, 720p BluRay 5.1CHDuration – 1hr 30minSubtitle – Myanmar HardsubFormat – Mp4Genre : Adventure, Comedy, DramaSource : 1080p.BluRayTranslator – ParrisEncoder – SWM",
    "screenshot_links": [
      "https://image.tmdb.org/t/p/w300/hiQDnX547RTEmdbsfUDoNnHLcxw.jpg",
      "https://image.tmdb.org/t/p/w300/qefyZuDt0qnLCIziSfxWKsiFCTV.jpg"
    ],
    "thumbnail_link": "https://channelmyanmar.org/wp-content/uploads/2020/08/Screen-Shot-2020-08-28-at-11.56.06-PM.png",
    "movie_links": [
      {
        "link": "https://usersdrive.com/nb65jmpcqx46.html",
        "server": "usersdrive.com",
        "size": "1.5 GB",
        "quality": "BluRay 1080P 5.1CH"
      },
      {
        "link": "https://usersdrive.com/o8dl4nuk43gd.html",
        "server": "usersdrive.com",
        "size": "780 MB",
        "quality": "BluRay 720P"
      },
      {
        "link": "https://yoteshinportal.cc/cm-the-wonderful-world-of-disney-princess-of-thieves-2001-blu-ray-1080-p-5-1-ch-mp-4",
        "server": "yoteshinportal.cc",
        "size": "1.5 GB",
        "quality": "BluRay 1080P 5.1CH"
      },
      {
        "link": "https://yoteshinportal.cc/cm-the-wonderful-world-of-disney-princess-of-thieves-2001-blu-ray-720-p-mp-4",
        "server": "yoteshinportal.cc",
        "size": "780 MB",
        "quality": "BluRay 720P"
      },
      {
        "link": "https://megaup.net/2Us3w/[CM]The.Wonderful.World.of.Disney.Princess.of.Thieves.2001.BluRay.1080P.5.1CH.mp4",
        "server": "megaup.net",
        "size": "1.5 GB",
        "quality": "BluRay 1080P 5.1CH"
      },
      {
        "link": "https://megaup.net/2euB3/[CM]The.Wonderful.World.of.Disney.Princess.of.Thieves.2001.BluRay.720P.mp4",
        "server": "megaup.net",
        "size": "780 MB",
        "quality": "BluRay 720P"
      },
      {
        "link": "https://upstream.to/3a3j3dy5lqwl",
        "server": "upstream.to",
        "size": "1.5 GB",
        "quality": "BluRay 1080P 5.1CH"
      },
      {
        "link": "https://upstream.to/poebxiqtrxgs",
        "server": "upstream.to",
        "size": "780 MB",
        "quality": "BluRay 720P"
      },
      {
        "link": "https://mega.nz/file/GsRwBQ6a#kAyxH--u8rACEodiOhlReuEBdkKMeCjG2zj9qRKCl9E",
        "server": "mega.nz",
        "size": "1.5 GB",
        "quality": "BluRay 1080P 5.1CH"
      },
      {
        "link": "https://mega.nz/file/CwByhKCA#4ico6G8LBS42EpTpYk7JbgOpCyz37N2YSuSgKj3CRRc",
        "server": "mega.nz",
        "size": "780 MB",
        "quality": "BluRay 720P"
      },
      {
        "link": "https://yadi.sk/i/-xyn0Vc26XmfNQ",
        "server": "disk.yandex.com",
        "size": "1.5 GB",
        "quality": "BluRay 1080P 5.1CH"
      },
      {
        "link": "https://yadi.sk/i/bXrkZZfi4XF3Tw",
        "server": "disk.yandex.com",
        "size": "780 MB",
        "quality": "BluRay 720P"
      }
    ],
    "trailer": null
  },
  {
    "metadata": "R|2001|2h 11min|Crime,Drama,Thriller",
    "rating": {
      "rating": "6.8/10",
      "rating_count": "265000"
    },
    "title": "Hannibal (2001)",
    "description": "Hannibal (2001)Cannibal ဆိုတဲ့အင်္ဂလိပ်စကားလုံးရဲ့အဓိပ္ပာယ်က လူသားစားတဲ့သူပေါ့။ ဒီလူသားစားတဲ့အရာကဘယ်လောက်ထိခရီးပေါက်နေလဲဆိုရင် cannibal တို့ cannibalism တို့ဆိုတဲ့စကားလုံးတွေကိုပါသုံးနေရတဲ့အထိပေါ့။ ဒီထဲကလူသတ်သမားက လူသားလည်းစားတဲ့ဇာတ်ကောင်မျိုး။ လူသတ်သမားဖြစ်တဲ့အတွက် သွေးအေးအေးနဲ့သတ်ပြီးတော့ကို ပယ်ပယ်နှယ်နှယ်စားတာမျိုးပေါ့။၊ ဇာတ်ကားတစ်လျှောက်လုံး စားပြမနေ၊သတ်ပြမနေပေမဲ့ ဇာတ်အိမ်ခိုင်ခိုင် ဇာတ်ကောင်ကောင်းကောင်းတွေနဲ့ ဇာတ်ကားတစ်လျှောက်လုံး ကြည့်ရှူသူပရိသတ်ကို မျောနေအောင်ဆွဲခေါ်သွားတာမျိုး။Triller/Crime လို့ genre သတ်မှတ်ထားပေမဲ့ Horror/Action ဆိုလည်းမမှားဘူးဗျ။ Triller/Crime ဆိုတဲ့အတိုင်း ရဲမှုခင်းဇာတ်ကားမျိုးပေါ့၊ လူသတ်သမားနဲ့စုံထောက်ကြားဇာတ်အိမ်ကောင်းကောင်းကိုဘယ်လိုတည်ဆောက်ထားလဲ တစိမ့်စိမ့် အရသာခံရင်းကြည့်ရမယ့်ကားမျိုး။ 1991 ကထွက်ခဲ့တဲ့ The Silence of the Lambs ဆိုတဲ့ IMDb 8.6/10 ရသွားပြီး 1991 ခုနှစ်အတွင်း တစ်ကမ္ဘာလုံးရဲ့ငါးကားမြောက်စာရင်းဝင်သွားတဲ့ Triller/Horror ကားတစ်ကားကိုတော့မှတ်မိကြမယ်ထင်ပါတယ်။ Triller/Horror ကြည့်သူတိုင်း ကြည့်ကိုကြည့်ထားသင့်တဲ့ကားကောင်းတစ်ကားပေါ့။ ဒီကားက အဲကားရဲ့ Sequel လို့ပြောလည်းရမယ့် ကားတစ်ကားပါပဲ။သုံးထားတဲ့ဘက်ဂျက်နဲ့ရုံတင်‌ဝင်ငွေပြန်ရခဲ့တဲ့ကားကောင်းတစ်ကားဖြစ်တာနဲ့အညီ‌ အတော်လေး ကြည့်လို့ကောင်းတာမျိုးကိုသွားတွေ့ရပါတယ်။ ဒီ Hannibal ကို inspiration ယူပြီးရိုက်ထားတဲ့ 2013 ခုနှစ်ကထွက်ခဲ့တဲ့ Hannibal စီရီးဟာဆိုရင်လည်း IMDb 8.5 ရတဲ့ထိကိုအောင်မြင်ခဲ့တယ်ပေါ့လေ။ ဆိုတော့ ဒီကားရဲ့ဇာတ်လမ်းအကျဉ်းကိုပြောရမယ်ဆိုရင် Hannibal Lector ဆိုတဲ့‌ လူသားစားလူသတ်သမားရဲ့လက်ကနေအသက်မသေဘဲလွတ်မြောက်လာခဲ့တဲ့ တစ်ဦးတည်းသောသားကောင်ဖြစ်တဲ့ Mason Verger ရယ်၊ အဲဒီလူသတ်သမားကို သရဲမရဲလိုက်ဖမ်းနေတဲ့အက်ဘီအိုင်အေးဂျင့် Clarice Starling ရယ်ဆိုပြီး အဓိကဇာတ်ကောင်သုံးယောက်ရဲ့အပြိုင်အဆိုင်အားပြိုင်မှုကိုတွေ့ရမယ်ပေါ့။ ဒါပေမဲ့ ဇာတ်လမ်းကောင်းတစ်ပုဒ်ဆိုတာ ဒီအဓိကဇာတ်‌ကောင်တွေတင်မကဘဲ အရံဇာတ်ကောင်ပေါင်းများစွာရဲ့ပံ့ပိုးမှုပါ ပါနေမယ်ဆိုတာသိပ်ပြောဖို့လိုမယ်မထင်ပါဘူး။ဒီတော့ 1999 ခုနှစ်ကထွက်ရှိခဲ့တဲ့ Thomas Harris ရဲ့ ဝတ္ထုရှည်ကိုရိုက်ကူးထားတဲ့ The Silence of the lambs ရဲ့ sequel ကားကောင်းတစ်ကားဖြစ်တဲ့ 21 ရာစုအစ 2001 ခုနှစ်ရဲ့ Hannibal ကားဟာ ဘယ်လောက်ကြည့်ကောင်းမယ်မကောင်းဘူးဆိုတော့ ရှု့စားဆုံးဖြတ်ပေးကြပါဦးခင်ဗျာ…(ဇာတ်ကားနဲ့ အညွှန်းကို San Thu Aung မှ ပြန်ဆိုရေးသားထားပါတယ်)Size – 2GB, 1.2GBQuality – 1080p, 720pIMDb Rating – 6.8/10Format – mp4Duration – 2H 11MinType – Thriller, CrimeSubtitle – Myanmar Subtitle (Hardsub)Translated by San Thu AungEncoded by Y",
    "screenshot_links": [
      "https://image.tmdb.org/t/p/w300/j2ugciy4ef6IwMDSnf5uDYPyMvc.jpg",
      "https://image.tmdb.org/t/p/w300/12hMR9EZwQyrRBrAfEVtrrKSoGP.jpg",
      "https://image.tmdb.org/t/p/w300/uMHtsquHKV55RivOOW6mEdYge0i.jpg",
      "https://image.tmdb.org/t/p/w300/lRpHFSeitaEezTFp7WMpDkRKIHy.jpg",
      "https://image.tmdb.org/t/p/w300/rqVDXaqiUgex70gljYu9fhoq1Os.jpg",
      "https://image.tmdb.org/t/p/w300/leoX6riSecG8zkfimFUQlfzTuGW.jpg",
      "https://image.tmdb.org/t/p/w300/zqEG6mfa48OiEOMJC2Mu6eAVLtt.jpg",
      "https://image.tmdb.org/t/p/w300/xVQhwqI8yBrKdMXgj9DJlhNsyV7.jpg",
      "https://image.tmdb.org/t/p/w300/k686FthVkWaBc0FJaP5P6g2aLqU.jpg",
      "https://image.tmdb.org/t/p/w300/i2nmKc0xqj4E4g1RiwXaQagNfsa.jpg",
      "https://image.tmdb.org/t/p/w300/1eMvglbY3wpl4nl09eYLtfstV2I.jpg",
      "https://image.tmdb.org/t/p/w300/2vpHOzugnxygD35BF7r5T4eQWxh.jpg",
      "https://image.tmdb.org/t/p/w300/hsui1hYKcCsgoNsO3zB0ICTgQPr.jpg",
      "https://image.tmdb.org/t/p/w300/5u2O0oUHhDppZfgctvBILx0PFmh.jpg"
    ],
    "thumbnail_link": "https://image.tmdb.org/t/p/w185/v5wAZwRqpGWmyAaaJ8BBHYuNXnj.jpg",
    "movie_links": [
      {
        "link": "https://www.cmvipmembers.com/check-movies/hannibal-2001",
        "server": "VIP Links",
        "size": "",
        "quality": ""
      },
      {
        "link": "https://yoteshinportal.cc/cm-hannibal-2001-1080-p-mp-4",
        "server": "yoteshinportal.cc",
        "size": "2GB",
        "quality": "1080p"
      },
      {
        "link": "https://yoteshinportal.cc/cm-hannibal-2001-720-p-mp-4",
        "server": "yoteshinportal.cc",
        "size": "1.2GB",
        "quality": "720p"
      },
      {
        "link": "https://mega.nz/file/9gs1XQpK#pBU8aUcD9iqD4_nW2bxqwxcSB2TYF076UEOcZ2qWqjE",
        "server": "mega.nz",
        "size": "2GB",
        "quality": "1080p"
      },
      {
        "link": "https://mega.nz/file/0g01HY5K#wXakmWsS2Hs0psyoE21c0GpfKMse2R6lJemkSPbX5ns",
        "server": "mega.nz",
        "size": "1.2GB",
        "quality": "720p"
      },
      {
        "link": "https://megaup.net/1Gwn4/(CM)_Hannibal_(2001)_1080p.mp4",
        "server": "megaup.net",
        "size": "2GB",
        "quality": "1080p"
      },
      {
        "link": "https://megaup.net/1Gwgl/(CM)_Hannibal_(2001)_720p.mp4",
        "server": "megaup.net",
        "size": "1.2GB",
        "quality": "720p"
      },
      {
        "link": "https://watchsb.com/yty92i3jn4rn.html",
        "server": "streamsb.com",
        "size": "1.2GB",
        "quality": "720p"
      }
    ],
    "trailer": {
      "video_id": "Lr3OavheNu0",
      "video_url": "https://www.youtube.com/watch?v=Lr3OavheNu0",
      "embed_url": "https://www.youtube.com/embed/Lr3OavheNu0"
    }
  },
  {
    "metadata": "PG|2001|90 min|Adventure,Animation,Comedy",
    "rating": {
      "rating": "7.9/10",
      "rating_count": "529,232"
    },
    "title": "Shrek (2001)",
    "description": "ဇာတ္လမ္းအက်ဥ္း~~~~~~~~~~~Dulocဆိုတဲ့ ၿမိဳ႕ေတာ္ႀကီးမွာ အၾကင္နာတရားေခါင္းပါးၿပီး တရားမမ်ွတမႈမ႐ွိတဲ့ တရားသူႀကီး Farquaadက Fairy Tale(နတ္သမီး ပံုျပင္)ေတြကို မႏွစ္သက္တဲ့အျပင္ သူ႔တို႔တိုင္းျပည္မွာ႐ိွေနတဲ့ Fairy Taleေတြထဲက သက္႐ွိဇာတ္ေကာင္ေတြ အားလံုးကို တိုင္းျပည္အစြန္ဖ်ားက ရႊံဗြက္ေတာႀကီးဆီကို နယ္ႏွင္ဒဏ္ေပးလိုက္ပါတယ္။အဲ့ဒီမွာလည္း…. Shrek(အစိမ္းေရာင္ ဘီလူးႀကီး)က လူသူကင္း႐ွင္းစြာနဲ႔ ၁ေယာက္တည္း ေပ်ာ္ရႊင္စြာ ေနထိုင္ေနပါတယ္။သူ႔ေနရာဆီကို နယ္ႏွင္ဒဏ္ေပးခံရတဲ့သူေတြ အမ်ားႀကီးလဲ ေရာက္လာေရာ… သူ႔ရဲ႕ေပ်ာ္ရႊင္မႈေတြ ပ်က္သြားတဲ့အတြက္….တရားသူႀကီး Farquaadဆီကို နယ္ႏွင္ဒဏ္ ျပန္႐ုတ္သိမ္းေပးဖို႔ သူနဲ႔အတူ Donkey (ပါးစပ္ပိတ္တာကလြဲလို႔ က်န္တာအကုန္လုပ္မယ့္ စကားအရမ္းမ်ားတဲ့ ျမည္း)က Dulocၿမိဳ႕ကို လမ္းျပပီး သြားမွာပါ။တရားသူႀကီး Farquaadကလည္း Cookie(စကားေျပာတတ္တဲ့ လူပံုစံမုန္႔)ေလးကို ႏွိပ္စက္ပီး က်န္႐ွိေနေသးတဲ့ Fairy Taleေတြထဲက ဇာတ္ေကာင္ေတြရဲ႕ ေနရာကို ေမးေနပါတယ္။ အဲ့ဒီအခ်ိန္မွာ… သူတပည့္ေတြက သူ႐ွာခိုင္းထားတဲ့ Magic Mirror (Snow Whiteထဲက Evil Queenရဲ႕ ေမွာ္မွန္)ကို သယ္လာပါတယ္။ အဲ့ေမွာ္မွန္ႀကီးကို “သူ႔ရဲ႕တိုင္းျပည္က တရားအမ်ွတဆံုးနဲ႔ ေအးခ်မ္းသာယာတဲ့ တိုင္းျပည္ျဖစ္ပီလား”လို႔ ေမးပါတယ္။ ေမွာ္မွန္ႀကီးက “Farquaadက ဘုရင္မွ မျဖစ္ေသးပဲနဲ႔.. ။ (သူက မင္းမ်ိဳးမင္းႏြယ္လဲ မဟုတ္တဲ့အတြက္) ဘုရင္ျဖစ္ခ်င္ရင္ မင္းသမီး၁ေယာက္ေယာက္ကို လက္ထပ္မွရမယ္”ဆိုပီး မင္းသမီး၃ေယာက္ကို ဘယ္သူ႔ႀကိဳက္လဲဆိုကာ သူ႔ေမွာ္မွန္မွာ ျပသ၍ ေရြးခ်ယ္ခိုင္းပါတယ္။အဲ့ဒီထဲကမွ Fionaဆိုတဲ့ မင္းသမီးကို ေရြးခ်ယ္လိုက္ပါတယ္။ (သူမက Farawayတိုင္းျပည္မွ ဘုရင့္သမီးျဖစ္ပီးေတာ့ အေစာင့္နဂါးႀကီး႐ွိတဲ့ ရဲတိုက္ႀကီးထဲမွာ သူမကို လာကယ္မယ့္ သူရဲေကာင္းကို စိတ္ကူးယဥ္ရင္း ဖမ္းခံထားရပါတယ္။)“မင္းသမီးက ညမွာျဖစ္တဲ့ကိစၥေလး၁ခုကပဲ…”ဆိုပီး ေမွာ္မွန္ႀကီးက Farquaadကို သတိေပးေျပာဆိုဖို႔ ႀကိဳးစားပါေသးတယ္။Dulocၿမိဳ႕ကို မေက်နပ္ခ်က္ေတြနဲ႔အတူေရာက္လာတဲ့ Shrekနဲ႔ Donkeyကို Farquaadက ဖမ္းခိုင္းပါတယ္။ သူတို႔ကို လာဖမ္းတဲ့ ရဲမက္ေတြကို အမိုက္စား Fightingနည္းေတြနဲ႔ Smack Downေတြ ေကြၽးပါတယ္ tongue emoticonဒါနဲ႔ေနာက္ေတာ့…. Fionaမင္းသမီးကို ကယ္ေပးႏိုင္ရင္ Farquaadက နယ္ႏွင္ဒဏ္ကို ႐ုတ္သိမ္းေပးမယ္ဆိုပီး Shrekနဲ႔ အေပးအယူလုပ္ပါတယ္။Shrekကလဲ အေပးအယူကို လက္ခံလိုက္ပါတယ္။ ……………………..~~~~~~~~~~~~~~~~~~~~~~Shrekနဲ႔ Donkeyက Fionaမင္းသမီးေလးကို နဂါးႀကီး လက္ထဲက ကယ္ႏိုင္မလား?တကယ္လို႔ ကယ္ႏိုင္ခဲ့ရင္ Shrekဆိုတဲ့ဘီလူးႀကီးကို မင္းသမီးေလးက သူ႔ရဲ႕ သူရဲေကာင္းအျဖစ္ ခ်စ္ႏိုင္မလား?Shrekက Fionaကို နယ္ႏွင္ဒဏ္နဲ႔ အလဲလွယ္လုပ္ရင္ Farquaadရဲ႕ ၾကင္ယာအျဖစ္ သိမ္းျခင္းကိုပဲ ခံရမလား?ဘာေတြဆက္ျဖစ္မလဲဆိုတာကို……….ဒီဇာတ္ကားရဲ႕ ေအာင္ျမင္မႈကဆိုရင္ျဖင့္ Shrek 2(2004), Shrek the Third (2007), Shrek Forever After (2010)ဆိုတဲ့ ေနာက္ဆက္တြဲကားေတြကို ျဖစ္ေပၚလာေစပါတယ္။Holiday specials ၂ခု Shrek the Halls (2007)နဲ႔ Scared Shrekless(2010)လဲ ႐ွိပါေသးတယ္။ပီးေတာ့ ဇာတ္လမ္းအခြဲျဖစ္တဲ့ Puss in Boots(2011)ကဆိုရင္လဲ ပရိသတ္ တခဲနက္အားေပးမႈေတြနဲ႔ ေအာင္ျမင္ထားပါတယ္။ =^.^=အၫႊန္းကို The biggest Animation Cartoon Fans (MM) https://www.facebook.com/groups/865029533533369/ မွ #Admin Thiha Maungက ေရးေပးထားတာ ျဖစ္ပါတယ္။File Size : (640 MB) and (300 MB)Quality : Blu-Ray 1080pRunning Time : 1hr 30minFormat : Mp4Genre : Animation, Adventure, ComedySubtitle : Myanmar Subtitle (Hard Sub)Source :  1080p.BluRay.x264.DTS-FGTTranslated by Nyi Than LwinEncoded by Thanhtike Zaw",
    "screenshot_links": [
      "https://image.tmdb.org/t/p/w300/wBG4kHfhwm3bLwKUFNRByXXv4r2.jpg",
      "https://image.tmdb.org/t/p/w300/13WHPYajhgFtaJjI28h28XOPt9I.jpg",
      "https://image.tmdb.org/t/p/w300/3l5CxSDIcWdtYne8m3BQDGOxFcl.jpg",
      "https://image.tmdb.org/t/p/w300/rpEPlKeVdQkX7oVojXATvgHlSzP.jpg",
      "https://image.tmdb.org/t/p/w300/9bebtcFnkkjIHWodFPCbYkSx1mq.jpg",
      "https://image.tmdb.org/t/p/w300/uP2MIdOPzSkOeouhT7xu10TNEL2.jpg",
      "https://image.tmdb.org/t/p/w300/52uYvs0JMlWjIcAvL0Pr8yZfrBm.jpg",
      "https://image.tmdb.org/t/p/w300/s3RmLACsT0sWKfiUkPvWHIcDnrt.jpg",
      "https://image.tmdb.org/t/p/w300/2l5UHZBcp9cx1PwKLdisJ0gV9jB.jpg",
      "https://image.tmdb.org/t/p/w300/zh87YxAZumcPz5pxQWEZ3AIxo6L.jpg"
    ],
    "thumbnail_link": "https://image.tmdb.org/t/p/w185/140ewbWv8qHStD3mlBDvvGd0Zvu.jpg",
    "movie_links": [
      {
        "link": "https://www.cmvipmembers.com/check-movies/shrek-2001",
        "server": "VIP Links",
        "size": "640 MB",
        "quality": ""
      },
      {
        "link": "https://cmdrive.net/d/shrek--2001--(mm-sub)-mp4",
        "server": "Google Drive",
        "size": "640 MB",
        "quality": ""
      },
      {
        "link": "https://yoteshinportal.cc/shrek-2001-mm-sub-mp-4",
        "server": "yoteshinportal.cc",
        "size": "640 MB",
        "quality": ""
      },
      {
        "link": "https://cmdrive.net/y/shrek--2001--(mm-sub)-mp4",
        "server": "disk.yandex.com",
        "size": "640 MB",
        "quality": ""
      },
      {
        "link": "https://megaup.net/U091/Shrek_[2001]_(MM_Sub).mp4",
        "server": "megaup.net",
        "size": "640 MB",
        "quality": ""
      }
    ],
    "trailer": {
      "video_id": "W37DlG1i61s",
      "video_url": "https://www.youtube.com/watch?v=W37DlG1i61s",
      "embed_url": "https://www.youtube.com/embed/W37DlG1i61s"
    }
  },
  {
    "metadata": "|2001|104 min|Adult,Asian,Thriller",
    "rating": {
      "rating": "5.4/10",
      "rating_count": "222"
    },
    "title": "[18+] Summertime (2001)",
    "description": "File Size…(700MB)Quality…DVDripFormat…mp4Duration…01:44:00Subtitle…Myanmar Subtitle(Hardsub)Encoder…RGBTranslated byMKK",
    "screenshot_links": [
      "https://image.tmdb.org/t/p/w300/tF8CmROc3DvQvRh3iH60fkZKkIR.jpg"
    ],
    "thumbnail_link": "https://channelmyanmar.org/wp-content/uploads/2017/09/51YayoMYEypWMtQ1iZwkyK9Dl5T.jpg",
    "movie_links": [
      {
        "link": "https://www.cmvipmembers.com/check-movies/summertime-sseommeotaim-18-2001",
        "server": "VIP Links",
        "size": "700 MB",
        "quality": "720p"
      },
      {
        "link": "https://yoteshinportal.cc/summertime-sseommeotaim-18-2001-mm-sub-mp-4",
        "server": "yoteshinportal.cc",
        "size": "700 MB",
        "quality": "720p"
      },
      {
        "link": " https://megaup.net/2suT2/Summertime_(Sseommeotaim)_[18+]_[2001]_(MM_Sub).mp4",
        "server": "megaup.net",
        "size": "700 MB",
        "quality": "720p"
      },
      {
        "link": "https://sbthe.com/4fy2ttau5z8t.html",
        "server": "streamsb.com",
        "size": "700 MB",
        "quality": "720p"
      }
    ],
    "trailer": null
  }
]